Workbook
Name DiscountRate: Assumptions!$B$15

Sheet Assumptions
A1: Driver | B1: Value
A2: EUR/USD rate | B2: 1.08
A3: SOFR | B3: 0.043
A4: Revolver spread | B4: 0.0225
A5: Steel price $/ton | B5: 850
A6: Container freight $/FEU | B6: 2400
A7: Import tariff rate | B7: 0.1
A8: Competitor list price $ | B8: 129
A9: Units sold, base year | B9: 100000
A10: Steel tons per unit | B10: 0.02
A11: Units per FEU | B11: 2000
A12: EUR cost per unit | B12: 45
A13: Revolver balance $ | B13: 5000000
... A15: Discount rate | B15: 0.1

Sheet P&L
B1: 2026 | C1: 2027 | D1: 2028 | E1: 2029 | F1: 2030
A2: Units | B2: =Assumptions!$B$9 -> 100000 | C2: =B2*1.08 -> 108000 | D2: =C2*1.08 -> 116640 | E2: =D2*1.08 -> 125971.2 | F2: =E2*1.08 -> 136048.9
A3: Price | B3: =Assumptions!$B$8*0.93 -> 119.97 | C3: =Assumptions!$B$8*0.93 -> 119.97 | D3: =Assumptions!$B$8*0.93 -> 119.97 | E3: =Assumptions!$B$8*0.93 -> 119.97 | F3: =Assumptions!$B$8*0.93 -> 119.97
A4: Revenue | B4: =B2*B3 -> 11997000 | C4: =C2*C3 -> 12956760 | D4: =D2*D3 -> 13993301 | E4: =E2*E3 -> 15112765 | F4: =F2*F3 -> 16321786
A5: Goods cost | B5: =B2*Assumptions!$B$12*Assumptions!$B$2 -> 4860000 | C5: =C2*Assumptions!$B$12*Assumptions!$B$2 -> 5248800 | D5: =D2*Assumptions!$B$12*Assumptions!$B$2 -> 5668704 | E5: =E2*Assumptions!$B$12*Assumptions!$B$2 -> 6122200.3 | F5: =F2*Assumptions!$B$12*Assumptions!$B$2 -> 6611976.3
A6: Steel | B6: =B2*Assumptions!$B$10*Assumptions!$B$5 -> 1700000 | C6: =C2*Assumptions!$B$10*Assumptions!$B$5 -> 1836000 | D6: =D2*Assumptions!$B$10*Assumptions!$B$5 -> 1982880 | E6: =E2*Assumptions!$B$10*Assumptions!$B$5 -> 2141510.4 | F6: =F2*Assumptions!$B$10*Assumptions!$B$5 -> 2312831.2
A7: Freight | B7: =B2/Assumptions!$B$11*Assumptions!$B$6 -> 120000 | C7: =C2/Assumptions!$B$11*Assumptions!$B$6 -> 129600 | D7: =D2/Assumptions!$B$11*Assumptions!$B$6 -> 139968 | E7: =E2/Assumptions!$B$11*Assumptions!$B$6 -> 151165.44 | F7: =F2/Assumptions!$B$11*Assumptions!$B$6 -> 163258.68
A8: Tariff | B8: =B5*Assumptions!$B$7 -> 486000 | C8: =C5*Assumptions!$B$7 -> 524880 | D8: =D5*Assumptions!$B$7 -> 566870.4 | E8: =E5*Assumptions!$B$7 -> 612220.03 | F8: =F5*Assumptions!$B$7 -> 661197.63
A9: COGS | B9: =SUM(B5:B8) -> 7166000 | C9: =SUM(C5:C8) -> 7739280 | D9: =SUM(D5:D8) -> 8358422.4 | E9: =SUM(E5:E8) -> 9027096.2 | F9: =SUM(F5:F8) -> 9749263.9
A10: Gross margin | B10: =B4-B9 -> 4831000 | C10: =C4-C9 -> 5217480 | D10: =D4-D9 -> 5634878.4 | E10: =E4-E9 -> 6085668.7 | F10: =F4-F9 -> 6572522.2
A11: Opex | B11: =Assumptions!$B$14 -> 1500000 | C11: =Assumptions!$B$14 -> 1500000 | D11: =Assumptions!$B$14 -> 1500000 | E11: =Assumptions!$B$14 -> 1500000 | F11: =Assumptions!$B$14 -> 1500000
A12: EBITDA | B12: =B10-B11 -> 3331000 | C12: =C10-C11 -> 3717480 | D12: =D10-D11 -> 4134878.4 | E12: =E10-E11 -> 4585668.7 | F12: =F10-F11 -> 5072522.2
A13: Interest | B13: =Assumptions!$B$13*(Assumptions!$B$3+Assumptions!$B$4) -> 327500 | C13: =Assumptions!$B$13*(Assumptions!$B$3+Assumptions!$B$4) -> 327500 | D13: =Assumptions!$B$13*(Assumptions!$B$3+Assumptions!$B$4) -> 327500 | E13: =Assumptions!$B$13*(Assumptions!$B$3+Assumptions!$B$4) -> 327500 | F13: =Assumptions!$B$13*(Assumptions!$B$3+Assumptions!$B$4) -> 327500
A14: Net income | B14: =ROUND((B12-B13)*(1-0.21),0) -> 2372765 | C14: =ROUND((C12-C13)*(1-0.21),0) -> 2678084 | D14: =ROUND((D12-D13)*(1-0.21),0) -> 3007829 | E14: =ROUND((E12-E13)*(1-0.21),0) -> 3363953 | F14: =ROUND((F12-F13)*(1-0.21),0) -> 3748568

Sheet DCF Summary
A2: NPV | B2: {=NPV(DiscountRate,'P&L'!B12:F12)} -> 15488785
A3: Total EBITDA | B3: =SUM('P&L'!B12:F12) -> 20841549
A4: Gross margin % 2030 | B4: ='P&L'!F10/'P&L'!F4 -> 0.402684
