Workbook

Sheet Cover
B2: Ridgeline Homes, Inc.
B3: Five-year operating model and DCF valuation
B5: Model date | C5: 45962
B6: Market inputs as of | C6: Close of 31-Oct-2025
B7: Prepared by | C7: FP&A / Corporate Development
B8: Version | C8: v1 - board pre-read, November 2025
B9: Currency / units | C9: US$ millions unless noted
B10: Fiscal year | C10: Calendar year (FY2025 = Jan-Dec 2025)
B12: Business | C12: US homebuilder selling entry-level and move-up single-family homes in the Southeast and Texas. Uses mortgage-rate buydowns as its main sales incentive.
B14: Tabs
B15: Assumptions | C15: Operating, market, policy and financing inputs
B16: P&L | C16: Revenue build, operating costs, EBITDA, interest, net income
B17: DCF | C17: WACC, unlevered free cash flow, NPV / enterprise and equity value
B19: Colour legend
B20: 1,234 | C20: Hardcoded input
B21: 1,234 | C21: Formula
B22: 1,234 | C22: Link to another tab
C23: Key output

Sheet Assumptions
A1: Ridgeline Homes, Inc. - Assumptions
A2: Model date 1-Nov-2025. Market inputs at close of 31-Oct-2025. US$ millions unless noted.
A4: Volumes and pricing | B4: Value | C4: Unit | H4: Source / note
A5: FY2024A home sales revenue | B5: 2760 | C5: $mm | H5: FY2024 audited financial statements
A6: Home closings, FY2025E | B6: 6050 | C6: homes | H6: 2025 community count and absorption plan
A7: Average selling price, FY2025E | B7: 478 | C7: $000 | H7: 2025 base price list
A8: Land and development cost, % of ASP | B8: 0.24 | C8: % | H8: Owned and optioned lot pipeline
A9: Direct construction cost per home | B9: 212 | C9: $000 | H9: 2025 trade contracts
A10: SG&A, % of revenue | B10: 0.095 | C10: % | H10: FY2024A run-rate
A11: D&A, % of revenue | B11: 0.008 | C11: % | H11: FY2024A run-rate
A12: Capex, % of revenue | B12: 0.007 | C12: % | H12: Model homes and IT
A13: Net working capital (inventory less payables), % of revenue | B13: 0.7 | C13: % | H13: FY2024A actual
A15: Market and policy inputs (close of 31-Oct-2025)
A16: 30-year fixed mortgage rate | B16: 0.0617 | C16: % | H16: Freddie Mac PMMS, FRED series MORTGAGE30US, week of 30-Oct-2025
A17: Bank prime loan rate | B17: 0.07 | C17: % | H17: FRED series DPRIME, 31-Oct-2025
A18: Conforming loan limit, one-unit baseline | B18: 806500 | C18: $ | H18: FHFA 2025 conforming loan limit
A19: US federal corporate income tax rate | B19: 0.21 | C19: % | H19: IRC section 11(b)
A21: Buydown incentive program
A22: Buydown target rate offered to buyers | B22: 0.0549 | C22: % | H22: Ridgeline Advantage program, October 2025
A23: Cost of a 100bp buydown, % of loan | B23: 0.045 | C23: % | H23: Affiliated lender quote
A24: Average buyer loan-to-value | B24: 0.85 | C24: % | H24: FY2024A buyer average
A26: Financing
A27: Land acquisition and development loans | B27: 620 | C27: $mm | H27: A&D facility at prime + margin; balance held flat
A28: A&D facility margin over prime | B28: 0.005 | C28: % | H28: A&D facility agreement
A29: Revolving credit facility, drawn | B29: 400 | C29: $mm | H29: SOFR + margin; balance held flat
A30: Revolver margin over SOFR | B30: 0.0175 | C30: % | H30: Credit agreement
A31: Senior notes due 2031 | B31: 1200 | C31: $mm | H31: Fixed coupon
A32: Senior notes coupon | B32: 0.0525 | C32: % | H32: Indenture
A33: Cash, 31-Oct-2025 | B33: 505 | C33: $mm | H33: Management accounts
A35: Growth | B35: FY2025E | C35: FY2026E | D35: FY2027E | E35: FY2028E | F35: FY2029E
A36: Closings growth, year on year | B36: 0.03 | C36: 0.04 | D36: 0.04 | E36: 0.035 | F36: 0.03 | H36: Community count plan
A37: ASP growth, year on year | B37: 0.025 | C37: 0.025 | D37: 0.025 | E37: 0.025 | F37: 0.025 | H37: Pricing plan

Sheet P&L
A1: Ridgeline Homes, Inc. - Income Statement
A2: US$ millions unless noted
B4: FY2024A | C4: FY2025E | D4: FY2026E | E4: FY2027E | F4: FY2028E | G4: FY2029E
A5: Closings growth | C5: ='Assumptions'!B36 -> 0.03 | D5: ='Assumptions'!C36 -> 0.04 | E5: ='Assumptions'!D36 -> 0.04 | F5: ='Assumptions'!E36 -> 0.035 | G5: ='Assumptions'!F36 -> 0.03
A6: ASP growth | C6: ='Assumptions'!B37 -> 0.025 | D6: ='Assumptions'!C37 -> 0.025 | E6: ='Assumptions'!D37 -> 0.025 | F6: ='Assumptions'!E37 -> 0.025 | G6: ='Assumptions'!F37 -> 0.025
A7: Home closings | C7: ='Assumptions'!$B$6 -> 6050 | D7: =C7*(1+'Assumptions'!C36) -> 6292 | E7: =D7*(1+'Assumptions'!D36) -> 6543.68 | F7: =E7*(1+'Assumptions'!E36) -> 6772.7088 | G7: =F7*(1+'Assumptions'!F36) -> 6975.8901
A8: Average selling price ($000) | C8: ='Assumptions'!$B$7 -> 478 | D8: =C8*(1+'Assumptions'!C37) -> 489.95 | E8: =D8*(1+'Assumptions'!D37) -> 502.19875 | F8: =E8*(1+'Assumptions'!E37) -> 514.75372 | G8: =F8*(1+'Assumptions'!F37) -> 527.62256
A10: Gross home sales revenue | C10: =C7*C8/1000 -> 2891.9 | D10: =D7*D8/1000 -> 3082.7654 | E10: =E7*E8/1000 -> 3286.2279 | F10: =F7*F8/1000 -> 3486.277 | G10: =G7*G8/1000 -> 3680.637
A11: Buydown incentive, % of revenue | C11: =MAX(0,'Assumptions'!$B$16-'Assumptions'!$B$22)*100*'Assumptions'!$B$23*'Assumptions'!$B$24 -> 0.02601 | D11: =MAX(0,'Assumptions'!$B$16-'Assumptions'!$B$22)*100*'Assumptions'!$B$23*'Assumptions'!$B$24 -> 0.02601 | E11: =MAX(0,'Assumptions'!$B$16-'Assumptions'!$B$22)*100*'Assumptions'!$B$23*'Assumptions'!$B$24 -> 0.02601 | F11: =MAX(0,'Assumptions'!$B$16-'Assumptions'!$B$22)*100*'Assumptions'!$B$23*'Assumptions'!$B$24 -> 0.02601 | G11: =MAX(0,'Assumptions'!$B$16-'Assumptions'!$B$22)*100*'Assumptions'!$B$23*'Assumptions'!$B$24 -> 0.02601
A12: Less: mortgage buydown incentives | C12: =-C10*C11 -> -75.218319 | D12: =-D10*D11 -> -80.182728 | E12: =-E10*E11 -> -85.474788 | F12: =-F10*F11 -> -90.678066 | G12: =-G10*G11 -> -95.733368
A13: Net home sales revenue | B13: ='Assumptions'!B5 -> 2760 | C13: =C10+C12 -> 2816.6817 | D13: =D10+D12 -> 3002.5827 | E13: =E10+E12 -> 3200.7531 | F13: =F10+F12 -> 3395.599 | G13: =G10+G12 -> 3584.9036
A15: Cost of sales
A16: Land and development | C16: =C10*'Assumptions'!$B$8 -> 694.056 | D16: =D10*'Assumptions'!$B$8 -> 739.8637 | E16: =E10*'Assumptions'!$B$8 -> 788.6947 | F16: =F10*'Assumptions'!$B$8 -> 836.70649 | G16: =G10*'Assumptions'!$B$8 -> 883.35288
A17: Direct construction | C17: =C7*'Assumptions'!$B$9/1000 -> 1282.6 | D17: =D7*'Assumptions'!$B$9/1000 -> 1333.904 | E17: =E7*'Assumptions'!$B$9/1000 -> 1387.2602 | F17: =F7*'Assumptions'!$B$9/1000 -> 1435.8143 | G17: =G7*'Assumptions'!$B$9/1000 -> 1478.8887
A18: Total cost of sales | C18: =C16+C17 -> 1976.656 | D18: =D16+D17 -> 2073.7677 | E18: =E16+E17 -> 2175.9549 | F18: =F16+F17 -> 2272.5208 | G18: =G16+G17 -> 2362.2416
A19: Gross profit | C19: =C13-C18 -> 840.02568 | D19: =D13-D18 -> 928.81498 | E19: =E13-E18 -> 1024.7983 | F19: =F13-F18 -> 1123.0782 | G19: =G13-G18 -> 1222.662
A20: Gross margin | C20: =C19/C13 -> 0.29823238 | D20: =D19/D13 -> 0.30933869 | E20: =E19/E13 -> 0.32017411 | F20: =F19/F13 -> 0.33074525 | G20: =G19/G13 -> 0.34105855
A21: SG&A | C21: =C13*'Assumptions'!$B$10 -> 267.58476 | D21: =D13*'Assumptions'!$B$10 -> 285.24535 | E21: =E13*'Assumptions'!$B$10 -> 304.07155 | F21: =F13*'Assumptions'!$B$10 -> 322.5819 | G21: =G13*'Assumptions'!$B$10 -> 340.56584
A22: EBITDA | C22: =C19-C21 -> 572.44092 | D22: =D19-D21 -> 643.56962 | E22: =E19-E21 -> 720.72672 | F22: =F19-F21 -> 800.49632 | G22: =G19-G21 -> 882.0962
A23: EBITDA margin | C23: =C22/C13 -> 0.20323238 | D23: =D22/D13 -> 0.21433869 | E23: =E22/E13 -> 0.22517411 | F23: =F22/F13 -> 0.23574525 | G23: =G22/G13 -> 0.24605855
A24: Depreciation and amortization | C24: =C13*'Assumptions'!$B$11 -> 22.533453 | D24: =D13*'Assumptions'!$B$11 -> 24.020661 | E24: =E13*'Assumptions'!$B$11 -> 25.606025 | F24: =F13*'Assumptions'!$B$11 -> 27.164792 | G24: =G13*'Assumptions'!$B$11 -> 28.679229
A25: EBIT | C25: =C22-C24 -> 549.90747 | D25: =D22-D24 -> 619.54896 | E25: =E22-E24 -> 695.1207 | F25: =F22-F24 -> 773.33153 | G25: =G22-G24 -> 853.41698
A27: Mortgage eligibility check
A28: Highest price financeable within conforming limit ($000) | C28: ='Assumptions'!$B$18/'Assumptions'!$B$24/1000 -> 948.82353 | D28: ='Assumptions'!$B$18/'Assumptions'!$B$24/1000 -> 948.82353 | E28: ='Assumptions'!$B$18/'Assumptions'!$B$24/1000 -> 948.82353 | F28: ='Assumptions'!$B$18/'Assumptions'!$B$24/1000 -> 948.82353 | G28: ='Assumptions'!$B$18/'Assumptions'!$B$24/1000 -> 948.82353
A29: ASP within conforming limit? | C29: =IF(C8<=C28,"Yes","No") -> Yes | D29: =IF(D8<=D28,"Yes","No") -> Yes | E29: =IF(E8<=E28,"Yes","No") -> Yes | F29: =IF(F8<=F28,"Yes","No") -> Yes | G29: =IF(G8<=G28,"Yes","No") -> Yes
A31: Financing
A32: Interest, A&D loans (prime + margin) | C32: ='Assumptions'!$B$27*('Assumptions'!$B$17+'Assumptions'!$B$28) -> 46.5 | D32: ='Assumptions'!$B$27*('Assumptions'!$B$17+'Assumptions'!$B$28) -> 46.5 | E32: ='Assumptions'!$B$27*('Assumptions'!$B$17+'Assumptions'!$B$28) -> 46.5 | F32: ='Assumptions'!$B$27*('Assumptions'!$B$17+'Assumptions'!$B$28) -> 46.5 | G32: ='Assumptions'!$B$27*('Assumptions'!$B$17+'Assumptions'!$B$28) -> 46.5
A33: Interest, revolver (SOFR + margin) | C33: ='Assumptions'!$B$29*(0.0422+'Assumptions'!$B$30) -> 23.88 | D33: ='Assumptions'!$B$29*(0.0422+'Assumptions'!$B$30) -> 23.88 | E33: ='Assumptions'!$B$29*(0.0422+'Assumptions'!$B$30) -> 23.88 | F33: ='Assumptions'!$B$29*(0.0422+'Assumptions'!$B$30) -> 23.88 | G33: ='Assumptions'!$B$29*(0.0422+'Assumptions'!$B$30) -> 23.88
A34: Interest, senior notes | C34: ='Assumptions'!$B$31*'Assumptions'!$B$32 -> 63 | D34: ='Assumptions'!$B$31*'Assumptions'!$B$32 -> 63 | E34: ='Assumptions'!$B$31*'Assumptions'!$B$32 -> 63 | F34: ='Assumptions'!$B$31*'Assumptions'!$B$32 -> 63 | G34: ='Assumptions'!$B$31*'Assumptions'!$B$32 -> 63
A35: Interest expense | C35: =C32+C33+C34 -> 133.38 | D35: =D32+D33+D34 -> 133.38 | E35: =E32+E33+E34 -> 133.38 | F35: =F32+F33+F34 -> 133.38 | G35: =G32+G33+G34 -> 133.38
A36: Blended cost of debt | C36: =C35/('Assumptions'!$B$27+'Assumptions'!$B$29+'Assumptions'!$B$31) -> 0.060081081 | D36: =D35/('Assumptions'!$B$27+'Assumptions'!$B$29+'Assumptions'!$B$31) -> 0.060081081 | E36: =E35/('Assumptions'!$B$27+'Assumptions'!$B$29+'Assumptions'!$B$31) -> 0.060081081 | F36: =F35/('Assumptions'!$B$27+'Assumptions'!$B$29+'Assumptions'!$B$31) -> 0.060081081 | G36: =G35/('Assumptions'!$B$27+'Assumptions'!$B$29+'Assumptions'!$B$31) -> 0.060081081
A37: Pre-tax income | C37: =C25-C35 -> 416.52747 | D37: =D25-D35 -> 486.16896 | E37: =E25-E35 -> 561.7407 | F37: =F25-F35 -> 639.95153 | G37: =G25-G35 -> 720.03698
A38: Income tax | C38: =MAX(C37,0)*'Assumptions'!$B$19 -> 87.470768 | D38: =MAX(D37,0)*'Assumptions'!$B$19 -> 102.09548 | E38: =MAX(E37,0)*'Assumptions'!$B$19 -> 117.96555 | F38: =MAX(F37,0)*'Assumptions'!$B$19 -> 134.38982 | G38: =MAX(G37,0)*'Assumptions'!$B$19 -> 151.20776
A39: Net income | C39: =C37-C38 -> 329.0567 | D39: =D37-D38 -> 384.07348 | E39: =E37-E38 -> 443.77515 | F39: =F37-F38 -> 505.5617 | G39: =G37-G38 -> 568.82921

Sheet DCF
A1: Ridgeline Homes, Inc. - DCF Valuation
A2: US$ millions unless noted. Unlevered free cash flow, end-of-period discounting.
A4: Discount rate (WACC) | H4: Source / note
A5: Valuation date | B5: =DATE(2025,11,1) -> 45962 | H5: Model date
A6: Risk-free rate (10-year US Treasury) | B6: 0.0411 | H6: FRED series DGS10, 31-Oct-2025
A7: Equity risk premium | B7: 0.05 | H7: House view
A8: Levered beta | B8: 1.6 | H8: Median of US homebuilder peers, 2-year weekly
A9: Size premium | B9: 0.01 | H9: House view
A10: Cost of equity | B10: =B6+B8*B7+B9 -> 0.1311 | H10: CAPM + size premium
A11: Pre-tax cost of debt | B11: ='P&L'!C36 -> 0.060081081 | H11: Blended cost of debt, FY2025E
A12: Tax rate | B12: ='Assumptions'!B19 -> 0.21
A13: After-tax cost of debt | B13: =B11*(1-B12) -> 0.047464054
A14: Target debt / total capital | B14: 0.3 | H14: Board-approved capital structure
A15: WACC | B15: =B10*(1-B14)+B13*B14 -> 0.10600922
A16: Terminal growth rate | B16: 0.025 | H16: House view, long-run nominal growth
A18: Unlevered free cash flow | C18: FY2025E | D18: FY2026E | E18: FY2027E | F18: FY2028E | G18: FY2029E
A19: Fiscal year end | C19: =DATE(2025,12,31) -> 46022 | D19: =DATE(YEAR(C19)+1,12,31) -> 46387 | E19: =DATE(YEAR(D19)+1,12,31) -> 46752 | F19: =DATE(YEAR(E19)+1,12,31) -> 47118 | G19: =DATE(YEAR(F19)+1,12,31) -> 47483
A20: EBITDA | C20: ='P&L'!C22 -> 572.44092 | D20: ='P&L'!D22 -> 643.56962 | E20: ='P&L'!E22 -> 720.72672 | F20: ='P&L'!F22 -> 800.49632 | G20: ='P&L'!G22 -> 882.0962
A21: Less: depreciation and amortization | C21: =-'P&L'!C24 -> -22.533453 | D21: =-'P&L'!D24 -> -24.020661 | E21: =-'P&L'!E24 -> -25.606025 | F21: =-'P&L'!F24 -> -27.164792 | G21: =-'P&L'!G24 -> -28.679229
A22: EBIT | C22: =C20+C21 -> 549.90747 | D22: =D20+D21 -> 619.54896 | E22: =E20+E21 -> 695.1207 | F22: =F20+F21 -> 773.33153 | G22: =G20+G21 -> 853.41698
A23: Less: taxes on EBIT | C23: =-MAX(C22,0)*$B$12 -> -115.48057 | D23: =-MAX(D22,0)*$B$12 -> -130.10528 | E23: =-MAX(E22,0)*$B$12 -> -145.97535 | F23: =-MAX(F22,0)*$B$12 -> -162.39962 | G23: =-MAX(G22,0)*$B$12 -> -179.21756
A24: Add back: depreciation and amortization | C24: =-C21 -> 22.533453 | D24: =-D21 -> 24.020661 | E24: =-E21 -> 25.606025 | F24: =-F21 -> 27.164792 | G24: =-G21 -> 28.679229
A25: Less: capex | C25: =-'P&L'!C13*'Assumptions'!$B$12 -> -19.716772 | D25: =-'P&L'!D13*'Assumptions'!$B$12 -> -21.018079 | E25: =-'P&L'!E13*'Assumptions'!$B$12 -> -22.405272 | F25: =-'P&L'!F13*'Assumptions'!$B$12 -> -23.769193 | G25: =-'P&L'!G13*'Assumptions'!$B$12 -> -25.094325
A26: Less: increase in net working capital | C26: =-('P&L'!C13-'P&L'!B13)*'Assumptions'!$B$13 -> -39.677177 | D26: =-('P&L'!D13-'P&L'!C13)*'Assumptions'!$B$13 -> -130.13069 | E26: =-('P&L'!E13-'P&L'!D13)*'Assumptions'!$B$13 -> -138.71932 | F26: =-('P&L'!F13-'P&L'!E13)*'Assumptions'!$B$13 -> -136.39209 | G26: =-('P&L'!G13-'P&L'!F13)*'Assumptions'!$B$13 -> -132.51325
A27: Unlevered free cash flow | C27: =SUM(C22:C26) -> 397.5664 | D27: =SUM(D22:D26) -> 362.31557 | E27: =SUM(E22:E26) -> 413.62678 | F27: =SUM(F22:F26) -> 477.93541 | G27: =SUM(G22:G26) -> 545.27106
A28: Share of year after valuation date | C28: =MIN(1,(C19-$B$5)/365) -> 0.16438356 | D28: =MIN(1,(D19-$B$5)/365) -> 1 | E28: =MIN(1,(E19-$B$5)/365) -> 1 | F28: =MIN(1,(F19-$B$5)/365) -> 1 | G28: =MIN(1,(G19-$B$5)/365) -> 1
A29: Free cash flow to discount | C29: =C27*C28 -> 65.353382 | D29: =D27*D28 -> 362.31557 | E29: =E27*E28 -> 413.62678 | F29: =F27*F28 -> 477.93541 | G29: =G27*G28 -> 545.27106
A30: Discount period (years) | C30: =(C19-$B$5)/365 -> 0.16438356 | D30: =(D19-$B$5)/365 -> 1.1643836 | E30: =(E19-$B$5)/365 -> 2.1643836 | F30: =(F19-$B$5)/365 -> 3.1671233 | G30: =(G19-$B$5)/365 -> 4.1671233
A31: Discount factor | C31: =1/(1+$B$15)^C30 -> 0.98357341 | D31: =1/(1+$B$15)^D30 -> 0.88929947 | E31: =1/(1+$B$15)^E30 -> 0.80406154 | F31: =1/(1+$B$15)^F30 -> 0.72679287 | G31: =1/(1+$B$15)^G30 -> 0.65713093
A32: Present value of free cash flow | C32: =C29*C31 -> 64.279849 | D32: =D29*D31 -> 322.20704 | E32: =E29*E31 -> 332.58139 | F32: =F29*F31 -> 347.36005 | G32: =G29*G31 -> 358.31448
A34: Valuation
A35: Sum of PV of free cash flow, FY2025E-FY2029E | B35: =SUM(C32:G32) -> 1424.7428
A36: Terminal value at end of FY2029E (Gordon growth) | B36: =G27*(1+B16)/(B15-B16) -> 6899.2501
A37: PV of terminal value | B37: =B36*G31 -> 4533.7106
A38: Enterprise value (NPV) | B38: =B35+B37 -> 5958.4534
A39: Less: debt outstanding | B39: =-('Assumptions'!B27+'Assumptions'!B29+'Assumptions'!B31) -> -2220 | H39: A&D loans + revolver + senior notes
A40: Add: cash | B40: ='Assumptions'!B33 -> 505
A41: Equity value | B41: =SUM(B38:B40) -> 4243.4534
A42: Implied EV / FY2025E EBITDA | B42: =B38/'P&L'!C22 -> 10.408853
A43: Terminal value share of enterprise value | B43: =B37/B38 -> 0.76088715
