Workbook

Sheet Cover
B2: Northstar Airways, Inc.
B3: Five-year operating model and DCF valuation
B5: Model date | C5: 45778
B6: Market inputs as of | C6: Close of 30-Apr-2025
B7: Prepared by | C7: FP&A / Corporate Development
B8: Version | C8: v1 - board pre-read, May 2025
B9: Currency / units | C9: US$ millions unless noted
B10: Fiscal year | C10: Calendar year (FY2025 = Jan-Dec 2025)
B12: Business | C12: US network airline flying a domestic hub network plus transpacific routes to Japan. Japan point-of-sale tickets are sold in JPY; fuel is bought at US Gulf Coast-linked prices and most of it is hedged with swaps.
B14: Tabs
B15: Assumptions | C15: Operating, market, policy and financing inputs
B16: P&L | C16: Revenue build, operating costs, EBITDA, interest, net income
B17: DCF | C17: WACC, unlevered free cash flow, NPV / enterprise and equity value
B19: Colour legend
B20: 1,234 | C20: Hardcoded input
B21: 1,234 | C21: Formula
B22: 1,234 | C22: Link to another tab
C23: Key output

Sheet Assumptions
A1: Northstar Airways, Inc. - Assumptions
A2: Model date 1-May-2025. Market inputs at close of 30-Apr-2025. US$ millions unless noted.
A4: Network and revenue | B4: Value | C4: Unit | H4: Source / note
A5: FY2024A operating revenue | B5: 7950 | C5: $mm | H5: FY2024 audited financial statements
A6: Available seat miles (ASMs), FY2025E | B6: 62 | C6: billions | H6: 2025 network plan
A7: Load factor | B7: 0.84 | C7: % | H7: FY2024A actual
A8: Domestic share of revenue passenger miles | B8: 0.7 | C8: % | H8: 2025 network plan
A9: Domestic gross fare yield, incl. ticket tax | B9: 17.2 | C9: cents/RPM | H9: FY2024A actual
A10: Transpacific revenue sold in JPY, FY2025E | B10: 260 | C10: ¥bn | H10: 2025 commercial plan, Japan point of sale
A11: Cargo and other revenue, % of passenger revenue | B11: 0.09 | C11: % | H11: FY2024A run-rate
A13: Market and policy inputs (close of 30-Apr-2025)
A14: Jet fuel, US Gulf Coast kerosene-type | B14: 1.909 | C14: $/gal | H14: EIA spot price, FRED series DJFUELUSGULF, 30-Apr-2025
A15: Federal excise tax on domestic passenger tickets | B15: 0.075 | C15: % | H15: 26 U.S.C. 4261(a)
A16: US federal corporate income tax rate | B16: 0.21 | C16: % | H16: IRC section 11(b)
A18: Fuel hedging
A19: Share of fuel consumption hedged | B19: 0.7 | C19: % | H19: Swap book at 30-Apr-2025, rolled forward each year
A20: Weighted average swap price | B20: 2.1 | C20: $/gal | H20: Swap book; fixed contract price
A22: Operating costs
A23: ASMs per gallon of fuel | B23: 82 | C23: ASM/gal | H23: FY2024A fleet average
A24: Labor cost per ASM | B24: 4.1 | C24: cents | H24: Labor contracts in force
A25: Other cost per ASM, ex fuel and labor | B25: 5 | C25: cents | H25: FY2024A run-rate
A26: D&A, % of revenue | B26: 0.055 | C26: % | H26: FY2024A run-rate
A27: Capex, % of revenue | B27: 0.055 | C27: % | H27: 2025-2029 fleet plan
A28: Net working capital, % of revenue | B28: -0.08 | C28: % | H28: Air traffic liability exceeds receivables
A30: Financing
A31: Aircraft-secured floating-rate debt, 31-Dec-2024 | B31: 4450 | C31: $mm | H31: Equipment notes; amortization paid each December
A32: Scheduled amortization, % of balance per year | B32: 0.06 | C32: % | H32: Equipment note schedules
A33: SOFR | B33: 0.0441 | C33: % | H33: NY Fed SOFR, FRED series SOFR, 30-Apr-2025
A34: Margin over SOFR | B34: 0.021 | C34: % | H34: Equipment note pricing
A35: Cash and short-term investments, 30-Apr-2025 | B35: 3000 | C35: $mm | H35: Management accounts
A37: Capacity growth | B37: FY2025E | C37: FY2026E | D37: FY2027E | E37: FY2028E | F37: FY2029E
A38: ASM growth, year on year | B38: 0.05 | C38: 0.045 | D38: 0.04 | E38: 0.04 | F38: 0.035 | H38: 2025-2029 fleet plan

Sheet P&L
A1: Northstar Airways, Inc. - Income Statement
A2: US$ millions unless noted
B4: FY2024A | C4: FY2025E | D4: FY2026E | E4: FY2027E | F4: FY2028E | G4: FY2029E
A5: Capacity growth | C5: ='Assumptions'!B38 -> 0.05 | D5: ='Assumptions'!C38 -> 0.045 | E5: ='Assumptions'!D38 -> 0.04 | F5: ='Assumptions'!E38 -> 0.04 | G5: ='Assumptions'!F38 -> 0.035
A6: ASMs (billions) | C6: ='Assumptions'!$B$6 -> 62 | D6: =C6*(1+'Assumptions'!C38) -> 64.79 | E6: =D6*(1+'Assumptions'!D38) -> 67.3816 | F6: =E6*(1+'Assumptions'!E38) -> 70.076864 | G6: =F6*(1+'Assumptions'!F38) -> 72.529554
A7: Domestic RPMs (billions) | C7: =C6*'Assumptions'!$B$7*'Assumptions'!$B$8 -> 36.456 | D7: =D6*'Assumptions'!$B$7*'Assumptions'!$B$8 -> 38.09652 | E7: =E6*'Assumptions'!$B$7*'Assumptions'!$B$8 -> 39.620381 | F7: =F6*'Assumptions'!$B$7*'Assumptions'!$B$8 -> 41.205196 | G7: =G6*'Assumptions'!$B$7*'Assumptions'!$B$8 -> 42.647378
A9: Operating revenue
A10: Domestic fares, gross of ticket tax | C10: =C7*'Assumptions'!$B$9*10 -> 6270.432 | D10: =D7*'Assumptions'!$B$9*10 -> 6552.6014 | E10: =E7*'Assumptions'!$B$9*10 -> 6814.7055 | F10: =F7*'Assumptions'!$B$9*10 -> 7087.2937 | G10: =G7*'Assumptions'!$B$9*10 -> 7335.349
A11: Less: federal ticket tax collected | C11: =-C10*'Assumptions'!$B$15/(1+'Assumptions'!$B$15) -> -437.472 | D11: =-D10*'Assumptions'!$B$15/(1+'Assumptions'!$B$15) -> -457.15824 | E11: =-E10*'Assumptions'!$B$15/(1+'Assumptions'!$B$15) -> -475.44457 | F11: =-F10*'Assumptions'!$B$15/(1+'Assumptions'!$B$15) -> -494.46235 | G11: =-G10*'Assumptions'!$B$15/(1+'Assumptions'!$B$15) -> -511.76853
A12: Domestic passenger revenue | C12: =C10+C11 -> 5832.96 | D12: =D10+D11 -> 6095.4432 | E12: =E10+E11 -> 6339.2609 | F12: =F10+F11 -> 6592.8314 | G12: =G10+G11 -> 6823.5805
A13: Transpacific sales in JPY (¥bn) | C13: ='Assumptions'!$B$10 -> 260 | D13: =C13*(1+'Assumptions'!C38) -> 271.7 | E13: =D13*(1+'Assumptions'!D38) -> 282.568 | F13: =E13*(1+'Assumptions'!E38) -> 293.87072 | G13: =F13*(1+'Assumptions'!F38) -> 304.1562
A14: Transpacific revenue, Japan POS | C14: =C13*1000/142.63 -> 1822.8984 | D14: =D13*1000/142.63 -> 1904.9288 | E14: =E13*1000/142.63 -> 1981.126 | F14: =F13*1000/142.63 -> 2060.371 | G14: =G13*1000/142.63 -> 2132.484
A15: Passenger revenue | C15: =C12+C14 -> 7655.8584 | D15: =D12+D14 -> 8000.372 | E15: =E12+E14 -> 8320.3869 | F15: =F12+F14 -> 8653.2024 | G15: =G12+G14 -> 8956.0645
A16: Cargo and other | C16: =C15*'Assumptions'!$B$11 -> 689.02726 | D16: =D15*'Assumptions'!$B$11 -> 720.03348 | E16: =E15*'Assumptions'!$B$11 -> 748.83482 | F16: =F15*'Assumptions'!$B$11 -> 778.78822 | G16: =G15*'Assumptions'!$B$11 -> 806.0458
A17: Total operating revenue | B17: ='Assumptions'!B5 -> 7950 | C17: =C15+C16 -> 8344.8857 | D17: =D15+D16 -> 8720.4055 | E17: =E15+E16 -> 9069.2217 | F17: =F15+F16 -> 9431.9906 | G17: =G15+G16 -> 9762.1103
A19: Operating expenses (ex D&A)
A20: Fuel consumed (million gallons) | C20: =C6*1000/'Assumptions'!$B$23 -> 756.09756 | D20: =D6*1000/'Assumptions'!$B$23 -> 790.12195 | E20: =E6*1000/'Assumptions'!$B$23 -> 821.72683 | F20: =F6*1000/'Assumptions'!$B$23 -> 854.5959 | G20: =G6*1000/'Assumptions'!$B$23 -> 884.50676
A21: Effective fuel price after hedges ($/gal) | C21: ='Assumptions'!$B$19*'Assumptions'!$B$20+(1-'Assumptions'!$B$19)*'Assumptions'!$B$14 -> 2.0427 | D21: ='Assumptions'!$B$19*'Assumptions'!$B$20+(1-'Assumptions'!$B$19)*'Assumptions'!$B$14 -> 2.0427 | E21: ='Assumptions'!$B$19*'Assumptions'!$B$20+(1-'Assumptions'!$B$19)*'Assumptions'!$B$14 -> 2.0427 | F21: ='Assumptions'!$B$19*'Assumptions'!$B$20+(1-'Assumptions'!$B$19)*'Assumptions'!$B$14 -> 2.0427 | G21: ='Assumptions'!$B$19*'Assumptions'!$B$20+(1-'Assumptions'!$B$19)*'Assumptions'!$B$14 -> 2.0427
A22: Aircraft fuel | C22: =C20*C21 -> 1544.4805 | D22: =D20*D21 -> 1613.9821 | E22: =E20*E21 -> 1678.5414 | F22: =F20*F21 -> 1745.683 | G22: =G20*G21 -> 1806.782
A23: Salaries, wages and benefits | C23: =C6*'Assumptions'!$B$24*10 -> 2542 | D23: =D6*'Assumptions'!$B$24*10 -> 2656.39 | E23: =E6*'Assumptions'!$B$24*10 -> 2762.6456 | F23: =F6*'Assumptions'!$B$24*10 -> 2873.1514 | G23: =G6*'Assumptions'!$B$24*10 -> 2973.7117
A24: Other operating expenses | C24: =C6*'Assumptions'!$B$25*10 -> 3100 | D24: =D6*'Assumptions'!$B$25*10 -> 3239.5 | E24: =E6*'Assumptions'!$B$25*10 -> 3369.08 | F24: =F6*'Assumptions'!$B$25*10 -> 3503.8432 | G24: =G6*'Assumptions'!$B$25*10 -> 3626.4777
A25: Total operating expenses (ex D&A) | C25: =C22+C23+C24 -> 7186.4805 | D25: =D22+D23+D24 -> 7509.8721 | E25: =E22+E23+E24 -> 7810.267 | F25: =F22+F23+F24 -> 8122.6777 | G25: =G22+G23+G24 -> 8406.9714
A26: EBITDA | C26: =C17-C25 -> 1158.4052 | D26: =D17-D25 -> 1210.5334 | E26: =E17-E25 -> 1258.9547 | F26: =F17-F25 -> 1309.3129 | G26: =G17-G25 -> 1355.1389
A27: EBITDA margin | C27: =C26/C17 -> 0.13881618 | D27: =D26/D17 -> 0.13881618 | E27: =E26/E17 -> 0.13881618 | F27: =F26/F17 -> 0.13881618 | G27: =G26/G17 -> 0.13881618
A28: Depreciation and amortization | C28: =C17*'Assumptions'!$B$26 -> 458.96871 | D28: =D17*'Assumptions'!$B$26 -> 479.6223 | E28: =E17*'Assumptions'!$B$26 -> 498.8072 | F28: =F17*'Assumptions'!$B$26 -> 518.75948 | G28: =G17*'Assumptions'!$B$26 -> 536.91607
A29: EBIT | C29: =C26-C28 -> 699.43647 | D29: =D26-D28 -> 730.91111 | E29: =E26-E28 -> 760.14755 | F29: =F26-F28 -> 790.55345 | G29: =G26-G28 -> 818.22282
A31: Financing
A32: Debt, opening | C32: ='Assumptions'!$B$31 -> 4450 | D32: =C33 -> 4183 | E32: =D33 -> 3916 | F32: =E33 -> 3649 | G32: =F33 -> 3382
A33: Debt, closing | C33: =MAX(C32-'Assumptions'!$B$31*'Assumptions'!$B$32,0) -> 4183 | D33: =MAX(D32-'Assumptions'!$B$31*'Assumptions'!$B$32,0) -> 3916 | E33: =MAX(E32-'Assumptions'!$B$31*'Assumptions'!$B$32,0) -> 3649 | F33: =MAX(F32-'Assumptions'!$B$31*'Assumptions'!$B$32,0) -> 3382 | G33: =MAX(G32-'Assumptions'!$B$31*'Assumptions'!$B$32,0) -> 3115
A34: Interest rate (SOFR + margin) | C34: ='Assumptions'!$B$33+'Assumptions'!$B$34 -> 0.0651 | D34: ='Assumptions'!$B$33+'Assumptions'!$B$34 -> 0.0651 | E34: ='Assumptions'!$B$33+'Assumptions'!$B$34 -> 0.0651 | F34: ='Assumptions'!$B$33+'Assumptions'!$B$34 -> 0.0651 | G34: ='Assumptions'!$B$33+'Assumptions'!$B$34 -> 0.0651
A35: Interest expense | C35: =AVERAGE(C32,C33)*C34 -> 281.00415 | D35: =AVERAGE(D32,D33)*D34 -> 263.62245 | E35: =AVERAGE(E32,E33)*E34 -> 246.24075 | F35: =AVERAGE(F32,F33)*F34 -> 228.85905 | G35: =AVERAGE(G32,G33)*G34 -> 211.47735
A36: Pre-tax income | C36: =C29-C35 -> 418.43232 | D36: =D29-D35 -> 467.28866 | E36: =E29-E35 -> 513.9068 | F36: =F29-F35 -> 561.6944 | G36: =G29-G35 -> 606.74547
A37: Income tax | C37: =MAX(C36,0)*'Assumptions'!$B$16 -> 87.870786 | D37: =MAX(D36,0)*'Assumptions'!$B$16 -> 98.130618 | E37: =MAX(E36,0)*'Assumptions'!$B$16 -> 107.92043 | F37: =MAX(F36,0)*'Assumptions'!$B$16 -> 117.95582 | G37: =MAX(G36,0)*'Assumptions'!$B$16 -> 127.41655
A38: Net income | C38: =C36-C37 -> 330.56153 | D38: =D36-D37 -> 369.15804 | E38: =E36-E37 -> 405.98637 | F38: =F36-F37 -> 443.73858 | G38: =G36-G37 -> 479.32892

Sheet DCF
A1: Northstar Airways, Inc. - DCF Valuation
A2: US$ millions unless noted. Unlevered free cash flow, end-of-period discounting.
A4: Discount rate (WACC) | H4: Source / note
A5: Valuation date | B5: =DATE(2025,5,1) -> 45778 | H5: Model date
A6: Risk-free rate (10-year US Treasury) | B6: 0.0417 | H6: FRED series DGS10, 30-Apr-2025
A7: Equity risk premium | B7: 0.05 | H7: House view
A8: Levered beta | B8: 1.4 | H8: Median of US network airline peers, 2-year weekly
A9: Size premium | B9: 0 | H9: House view
A10: Cost of equity | B10: =B6+B8*B7+B9 -> 0.1117 | H10: CAPM + size premium
A11: Pre-tax cost of debt | B11: ='P&L'!C34 -> 0.0651 | H11: Equipment note all-in rate, FY2025E
A12: Tax rate | B12: ='Assumptions'!B16 -> 0.21
A13: After-tax cost of debt | B13: =B11*(1-B12) -> 0.051429
A14: Target debt / total capital | B14: 0.4 | H14: Board-approved capital structure
A15: WACC | B15: =B10*(1-B14)+B13*B14 -> 0.0875916
A16: Terminal growth rate | B16: 0.02 | H16: House view, long-run nominal growth
A18: Unlevered free cash flow | C18: FY2025E | D18: FY2026E | E18: FY2027E | F18: FY2028E | G18: FY2029E
A19: Fiscal year end | C19: =DATE(2025,12,31) -> 46022 | D19: =DATE(YEAR(C19)+1,12,31) -> 46387 | E19: =DATE(YEAR(D19)+1,12,31) -> 46752 | F19: =DATE(YEAR(E19)+1,12,31) -> 47118 | G19: =DATE(YEAR(F19)+1,12,31) -> 47483
A20: EBITDA | C20: ='P&L'!C26 -> 1158.4052 | D20: ='P&L'!D26 -> 1210.5334 | E20: ='P&L'!E26 -> 1258.9547 | F20: ='P&L'!F26 -> 1309.3129 | G20: ='P&L'!G26 -> 1355.1389
A21: Less: depreciation and amortization | C21: =-'P&L'!C28 -> -458.96871 | D21: =-'P&L'!D28 -> -479.6223 | E21: =-'P&L'!E28 -> -498.8072 | F21: =-'P&L'!F28 -> -518.75948 | G21: =-'P&L'!G28 -> -536.91607
A22: EBIT | C22: =C20+C21 -> 699.43647 | D22: =D20+D21 -> 730.91111 | E22: =E20+E21 -> 760.14755 | F22: =F20+F21 -> 790.55345 | G22: =G20+G21 -> 818.22282
A23: Less: taxes on EBIT | C23: =-MAX(C22,0)*$B$12 -> -146.88166 | D23: =-MAX(D22,0)*$B$12 -> -153.49133 | E23: =-MAX(E22,0)*$B$12 -> -159.63099 | F23: =-MAX(F22,0)*$B$12 -> -166.01623 | G23: =-MAX(G22,0)*$B$12 -> -171.82679
A24: Add back: depreciation and amortization | C24: =-C21 -> 458.96871 | D24: =-D21 -> 479.6223 | E24: =-E21 -> 498.8072 | F24: =-F21 -> 518.75948 | G24: =-G21 -> 536.91607
A25: Less: capex | C25: =-'P&L'!C17*'Assumptions'!$B$27 -> -458.96871 | D25: =-'P&L'!D17*'Assumptions'!$B$27 -> -479.6223 | E25: =-'P&L'!E17*'Assumptions'!$B$27 -> -498.8072 | F25: =-'P&L'!F17*'Assumptions'!$B$27 -> -518.75948 | G25: =-'P&L'!G17*'Assumptions'!$B$27 -> -536.91607
A26: Less: increase in net working capital | C26: =-('P&L'!C17-'P&L'!B17)*'Assumptions'!$B$28 -> 31.590853 | D26: =-('P&L'!D17-'P&L'!C17)*'Assumptions'!$B$28 -> 30.041588 | E26: =-('P&L'!E17-'P&L'!D17)*'Assumptions'!$B$28 -> 27.905298 | F26: =-('P&L'!F17-'P&L'!E17)*'Assumptions'!$B$28 -> 29.02151 | G26: =-('P&L'!G17-'P&L'!F17)*'Assumptions'!$B$28 -> 26.409574
A27: Unlevered free cash flow | C27: =SUM(C22:C26) -> 584.14566 | D27: =SUM(D22:D26) -> 607.46136 | E27: =SUM(E22:E26) -> 628.42186 | F27: =SUM(F22:F26) -> 653.55874 | G27: =SUM(G22:G26) -> 672.8056
A28: Share of year after valuation date | C28: =MIN(1,(C19-$B$5)/365) -> 0.66849315 | D28: =MIN(1,(D19-$B$5)/365) -> 1 | E28: =MIN(1,(E19-$B$5)/365) -> 1 | F28: =MIN(1,(F19-$B$5)/365) -> 1 | G28: =MIN(1,(G19-$B$5)/365) -> 1
A29: Free cash flow to discount | C29: =C27*C28 -> 390.49737 | D29: =D27*D28 -> 607.46136 | E29: =E27*E28 -> 628.42186 | F29: =F27*F28 -> 653.55874 | G29: =G27*G28 -> 672.8056
A30: Discount period (years) | C30: =(C19-$B$5)/365 -> 0.66849315 | D30: =(D19-$B$5)/365 -> 1.6684932 | E30: =(E19-$B$5)/365 -> 2.6684932 | F30: =(F19-$B$5)/365 -> 3.6712329 | G30: =(G19-$B$5)/365 -> 4.6712329
A31: Discount factor | C31: =1/(1+$B$15)^C30 -> 0.94541575 | D31: =1/(1+$B$15)^D30 -> 0.8692746 | E31: =1/(1+$B$15)^E30 -> 0.79926564 | F31: =1/(1+$B$15)^F30 -> 0.73472597 | G31: =1/(1+$B$15)^G30 -> 0.67555319
A32: Present value of free cash flow | C32: =C29*C31 -> 369.18237 | D32: =D29*D31 -> 528.05073 | E32: =E29*E31 -> 502.276 | F32: =F29*F31 -> 480.18658 | G32: =G29*G31 -> 454.51597
A34: Valuation
A35: Sum of PV of free cash flow, FY2025E-FY2029E | B35: =SUM(C32:G32) -> 2334.2116
A36: Terminal value at end of FY2029E (Gordon growth) | B36: =G27*(1+B16)/(B15-B16) -> 10153.062
A37: PV of terminal value | B37: =B36*G31 -> 6858.9335
A38: Enterprise value (NPV) | B38: =B35+B37 -> 9193.1452
A39: Less: debt outstanding | B39: =-'Assumptions'!B31 -> -4450 | H39: Amortization is paid in December, so the 31-Dec-2024 balance is still outstanding
A40: Add: cash | B40: ='Assumptions'!B35 -> 3000
A41: Equity value | B41: =SUM(B38:B40) -> 7743.1452
A42: Implied EV / FY2025E EBITDA | B42: =B38/'P&L'!C26 -> 7.936036
A43: Terminal value share of enterprise value | B43: =B37/B38 -> 0.74609216
