Workbook

Sheet Cover
B2: Keystone Freight Lines, Inc.
B3: Five-year operating model and DCF valuation
B5: Model date | C5: 46082
B6: Market inputs as of | C6: Close of 27-Feb-2026
B7: Prepared by | C7: FP&A / Corporate Development
B8: Version | C8: v1 - board pre-read, March 2026
B9: Currency / units | C9: US$ millions unless noted
B10: Fiscal year | C10: Calendar year (FY2026 = Jan-Dec 2026)
B12: Business | C12: US truckload carrier running dry-van and cross-border lanes into Canada and Mexico. Canadian freight is billed in CAD; the Mexico terminal and drayage network is paid in MXN.
B14: Tabs
B15: Assumptions | C15: Operating, market, policy and financing inputs
B16: P&L | C16: Revenue build, operating costs, EBITDA, interest, net income
B17: DCF | C17: WACC, unlevered free cash flow, NPV / enterprise and equity value
B19: Colour legend
B20: 1,234 | C20: Hardcoded input
B21: 1,234 | C21: Formula
B22: 1,234 | C22: Link to another tab
C23: Key output

Sheet Assumptions
A1: Keystone Freight Lines, Inc. - Assumptions
A2: Model date 1-Mar-2026. Market inputs at close of 27-Feb-2026. US$ millions unless noted.
A4: Volumes and pricing | B4: Value | C4: Unit | H4: Source / note
A5: FY2025A operating revenue | B5: 3050 | C5: $mm | H5: FY2025 audited financial statements
A6: Total miles, FY2026E | B6: 980 | C6: million | H6: 2026 network plan
A7: Linehaul revenue per mile, ex fuel surcharge | B7: 2.45 | C7: $/mile | H7: 2026 contract rates
A8: Fuel surcharge base (peg) price | B8: 1.25 | C8: $/gal | H8: Customer contract fuel surcharge schedule
A9: Fuel surcharge mpg | B9: 6 | C9: mpg | H9: Customer contract fuel surcharge schedule
A10: Share of miles covered by fuel surcharge | B10: 0.85 | C10: % | H10: FY2025A actual
A11: Canada cross-border revenue, FY2026E | B11: 420 | C11: C$mm | H11: Billed in CAD
A12: Mexico terminal and drayage costs, FY2026E | B12: 3150 | C12: MXN mm | H12: Paid in MXN
A13: Fleet fuel economy | B13: 6.9 | C13: mpg | H13: FY2025A fleet average
A14: Tractors in service, FY2026E | B14: 6500 | C14: tractors | H14: Fleet plan
A15: Driver wages and benefits per mile | B15: 0.95 | C15: $/mile | H15: 2026 driver pay plan
A16: Maintenance per mile | B16: 0.21 | C16: $/mile | H16: FY2025A run-rate
... A21: Net working capital, % of revenue | B21: 0.06 | C21: % | H21: FY2025A actual
A23: Market and policy inputs (close of 27-Feb-2026)
A24: On-highway diesel, US average retail | B24: 3.809 | C24: $/gal | H24: EIA weekly, FRED series GASDESW, week of 23-Feb-2026
A25: USD/CAD exchange rate | B25: 1.3632 | C25: C$ per $ | H25: Fed H.10 noon buying rate, FRED series DEXCAUS, 27-Feb-2026
A26: Federal heavy vehicle use tax, per tractor | B26: 550 | C26: $/year | H26: 26 U.S.C. 4481, vehicles over 75,000 lbs
A27: US federal corporate income tax rate | B27: 0.21 | C27: % | H27: IRC section 11(b)
A29: Financing
A30: Equipment financing balance, 31-Dec-2025 | B30: 1100 | C30: $mm | H30: Floating-rate equipment notes; amortization paid each December
A31: Scheduled amortization, % of balance per year | B31: 0.1 | C31: % | H31: Equipment note schedules
A32: Margin over SOFR | B32: 0.0185 | C32: % | H32: Equipment note pricing
A33: Cash, 27-Feb-2026 | B33: 140 | C33: $mm | H33: Management accounts
A35: Growth | B35: FY2026E | C35: FY2027E | D35: FY2028E | E35: FY2029E | F35: FY2030E
A36: Miles growth, year on year | B36: 0.03 | C36: 0.035 | D36: 0.035 | E36: 0.03 | F36: 0.03 | H36: Network plan
A37: Rate per mile growth, year on year | B37: 0.02 | C37: 0.025 | D37: 0.025 | E37: 0.02 | F37: 0.02 | H37: Contract renewal plan

Sheet P&L
A1: Keystone Freight Lines, Inc. - Income Statement
A2: US$ millions unless noted
B4: FY2025A | C4: FY2026E | D4: FY2027E | E4: FY2028E | F4: FY2029E | G4: FY2030E
A5: Miles growth | C5: ='Assumptions'!B36 -> 0.03 | D5: ='Assumptions'!C36 -> 0.035 | E5: ='Assumptions'!D36 -> 0.035 | F5: ='Assumptions'!E36 -> 0.03 | G5: ='Assumptions'!F36 -> 0.03
A6: Rate per mile growth | C6: ='Assumptions'!B37 -> 0.02 | D6: ='Assumptions'!C37 -> 0.025 | E6: ='Assumptions'!D37 -> 0.025 | F6: ='Assumptions'!E37 -> 0.02 | G6: ='Assumptions'!F37 -> 0.02
A7: Total miles (million) | C7: ='Assumptions'!$B$6 -> 980 | D7: =C7*(1+'Assumptions'!C36) -> 1014.3 | E7: =D7*(1+'Assumptions'!D36) -> 1049.8005 | F7: =E7*(1+'Assumptions'!E36) -> 1081.2945 | G7: =F7*(1+'Assumptions'!F36) -> 1113.7334
A8: Linehaul revenue per mile ($) | C8: ='Assumptions'!$B$7 -> 2.45 | D8: =C8*(1+'Assumptions'!C37) -> 2.51125 | E8: =D8*(1+'Assumptions'!D37) -> 2.5740312 | F8: =E8*(1+'Assumptions'!E37) -> 2.6255119 | G8: =F8*(1+'Assumptions'!F37) -> 2.6780221
A10: Operating revenue
A11: Linehaul revenue | C11: =C7*C8 -> 2401 | D11: =D7*D8 -> 2547.1609 | E11: =E7*E8 -> 2702.2193 | F11: =F7*F8 -> 2838.9516 | G11: =G7*G8 -> 2982.6025
A12: Fuel surcharge revenue | C12: =C7*MAX(0,'Assumptions'!$B$24-'Assumptions'!$B$8)/'Assumptions'!$B$9*'Assumptions'!$B$10 -> 355.2745 | D12: =D7*MAX(0,'Assumptions'!$B$24-'Assumptions'!$B$8)/'Assumptions'!$B$9*'Assumptions'!$B$10 -> 367.70911 | E12: =E7*MAX(0,'Assumptions'!$B$24-'Assumptions'!$B$8)/'Assumptions'!$B$9*'Assumptions'!$B$10 -> 380.57893 | F12: =F7*MAX(0,'Assumptions'!$B$24-'Assumptions'!$B$8)/'Assumptions'!$B$9*'Assumptions'!$B$10 -> 391.99629 | G12: =G7*MAX(0,'Assumptions'!$B$24-'Assumptions'!$B$8)/'Assumptions'!$B$9*'Assumptions'!$B$10 -> 403.75618
A13: Canada cross-border revenue (C$mm) | C13: ='Assumptions'!$B$11 -> 420 | D13: =C13*(1+'Assumptions'!C36) -> 434.7 | E13: =D13*(1+'Assumptions'!D36) -> 449.9145 | F13: =E13*(1+'Assumptions'!E36) -> 463.41194 | G13: =F13*(1+'Assumptions'!F36) -> 477.31429
A14: Canada cross-border revenue | C14: =C13/'Assumptions'!$B$25 -> 308.09859 | D14: =D13/'Assumptions'!$B$25 -> 318.88204 | E14: =E13/'Assumptions'!$B$25 -> 330.04291 | F14: =F13/'Assumptions'!$B$25 -> 339.9442 | G14: =G13/'Assumptions'!$B$25 -> 350.14253
A15: Total operating revenue | B15: ='Assumptions'!B5 -> 3050 | C15: =C11+C12+C14 -> 3064.3731 | D15: =D11+D12+D14 -> 3233.752 | E15: =E11+E12+E14 -> 3412.8411 | F15: =F11+F12+F14 -> 3570.8921 | G15: =G11+G12+G14 -> 3736.5012
A16: Revenue excluding fuel surcharge | C16: =C15-C12 -> 2709.0986 | D16: =D15-D12 -> 2866.0429 | E16: =E15-E12 -> 3032.2622 | F16: =F15-F12 -> 3178.8958 | G16: =G15-G12 -> 3332.7451
A18: Operating expenses (ex D&A)
A19: Diesel consumed (million gal) | C19: =C7/'Assumptions'!$B$13 -> 142.02899 | D19: =D7/'Assumptions'!$B$13 -> 147 | E19: =E7/'Assumptions'!$B$13 -> 152.145 | F19: =F7/'Assumptions'!$B$13 -> 156.70935 | G19: =G7/'Assumptions'!$B$13 -> 161.41063
A20: Fuel | C20: =C19*'Assumptions'!$B$24 -> 540.98841 | D20: =D19*'Assumptions'!$B$24 -> 559.923 | E20: =E19*'Assumptions'!$B$24 -> 579.52031 | F20: =F19*'Assumptions'!$B$24 -> 596.90591 | G20: =G19*'Assumptions'!$B$24 -> 614.81309
A21: Driver wages and benefits | C21: =C7*'Assumptions'!$B$15 -> 931 | D21: =D7*'Assumptions'!$B$15 -> 963.585 | E21: =E7*'Assumptions'!$B$15 -> 997.31047 | F21: =F7*'Assumptions'!$B$15 -> 1027.2298 | G21: =G7*'Assumptions'!$B$15 -> 1058.0467
A22: Maintenance | C22: =C7*'Assumptions'!$B$16 -> 205.8 | D22: =D7*'Assumptions'!$B$16 -> 213.003 | E22: =E7*'Assumptions'!$B$16 -> 220.4581 | F22: =F7*'Assumptions'!$B$16 -> 227.07185 | G22: =G7*'Assumptions'!$B$16 -> 233.884
A23: Insurance and claims | C23: =C7*'Assumptions'!$B$17 -> 137.2 | D23: =D7*'Assumptions'!$B$17 -> 142.002 | E23: =E7*'Assumptions'!$B$17 -> 146.97207 | F23: =F7*'Assumptions'!$B$17 -> 151.38123 | G23: =G7*'Assumptions'!$B$17 -> 155.92267
A24: Tractors in service | C24: ='Assumptions'!$B$14 -> 6500 | D24: =C24*(1+'Assumptions'!C36) -> 6727.5 | E24: =D24*(1+'Assumptions'!D36) -> 6962.9625 | F24: =E24*(1+'Assumptions'!E36) -> 7171.8514 | G24: =F24*(1+'Assumptions'!F36) -> 7387.0069
A25: Heavy vehicle use tax | C25: =C24*'Assumptions'!$B$26/1000000 -> 3.575 | D25: =D24*'Assumptions'!$B$26/1000000 -> 3.700125 | E25: =E24*'Assumptions'!$B$26/1000000 -> 3.8296294 | F25: =F24*'Assumptions'!$B$26/1000000 -> 3.9445183 | G25: =G24*'Assumptions'!$B$26/1000000 -> 4.0628538
A26: Mexico terminal and drayage costs (MXN mm) | C26: ='Assumptions'!$B$12 -> 3150 | D26: =C26*(1+'Assumptions'!C36) -> 3260.25 | E26: =D26*(1+'Assumptions'!D36) -> 3374.3587 | F26: =E26*(1+'Assumptions'!E36) -> 3475.5895 | G26: =F26*(1+'Assumptions'!F36) -> 3579.8572
A27: Mexico terminal and drayage costs | C27: =C26/17.2207 -> 182.91939 | D27: =D26/17.2207 -> 189.32157 | E27: =E26/17.2207 -> 195.94783 | F27: =F26/17.2207 -> 201.82626 | G27: =G26/17.2207 -> 207.88105
A28: Other operating expenses | C28: =C16*'Assumptions'!$B$18 -> 379.2738 | D28: =D16*'Assumptions'!$B$18 -> 401.24601 | E28: =E16*'Assumptions'!$B$18 -> 424.51671 | F28: =F16*'Assumptions'!$B$18 -> 445.04541 | G28: =G16*'Assumptions'!$B$18 -> 466.58431
A29: Total operating expenses (ex D&A) | C29: =C20+C21+C22+C23+C25+C27+C28 -> 2380.7566 | D29: =D20+D21+D22+D23+D25+D27+D28 -> 2472.7807 | E29: =E20+E21+E22+E23+E25+E27+E28 -> 2568.5551 | F29: =F20+F21+F22+F23+F25+F27+F28 -> 2653.405 | G29: =G20+G21+G22+G23+G25+G27+G28 -> 2741.1947
A30: EBITDA | C30: =C15-C29 -> 683.61649 | D30: =D15-D29 -> 760.97132 | E30: =E15-E29 -> 844.28601 | F30: =F15-F29 -> 917.48711 | G30: =G15-G29 -> 995.30659
A31: EBITDA margin | C31: =C30/C15 -> 0.22308527 | D31: =D30/D15 -> 0.23532148 | E31: =E30/E15 -> 0.24738509 | F31: =F30/F15 -> 0.25693499 | G31: =G30/G15 -> 0.26637395
A32: Depreciation and amortization | C32: =C16*'Assumptions'!$B$19 -> 243.81887 | D32: =D16*'Assumptions'!$B$19 -> 257.94386 | E32: =E16*'Assumptions'!$B$19 -> 272.9036 | F32: =F16*'Assumptions'!$B$19 -> 286.10062 | G32: =G16*'Assumptions'!$B$19 -> 299.94706
A33: EBIT | C33: =C30-C32 -> 439.79762 | D33: =D30-D32 -> 503.02746 | E33: =E30-E32 -> 571.38241 | F33: =F30-F32 -> 631.38649 | G33: =G30-G32 -> 695.35953
A35: Financing
A36: Debt, opening | C36: ='Assumptions'!$B$30 -> 1100 | D36: =C37 -> 990 | E36: =D37 -> 880 | F36: =E37 -> 770 | G36: =F37 -> 660
A37: Debt, closing | C37: =MAX(C36-'Assumptions'!$B$30*'Assumptions'!$B$31,0) -> 990 | D37: =MAX(D36-'Assumptions'!$B$30*'Assumptions'!$B$31,0) -> 880 | E37: =MAX(E36-'Assumptions'!$B$30*'Assumptions'!$B$31,0) -> 770 | F37: =MAX(F36-'Assumptions'!$B$30*'Assumptions'!$B$31,0) -> 660 | G37: =MAX(G36-'Assumptions'!$B$30*'Assumptions'!$B$31,0) -> 550
A38: Interest rate (SOFR + margin) | C38: =0.0368+'Assumptions'!$B$32 -> 0.0553 | D38: =0.0368+'Assumptions'!$B$32 -> 0.0553 | E38: =0.0368+'Assumptions'!$B$32 -> 0.0553 | F38: =0.0368+'Assumptions'!$B$32 -> 0.0553 | G38: =0.0368+'Assumptions'!$B$32 -> 0.0553
A39: Interest expense | C39: =AVERAGE(C36,C37)*C38 -> 57.7885 | D39: =AVERAGE(D36,D37)*D38 -> 51.7055 | E39: =AVERAGE(E36,E37)*E38 -> 45.6225 | F39: =AVERAGE(F36,F37)*F38 -> 39.5395 | G39: =AVERAGE(G36,G37)*G38 -> 33.4565
A40: Pre-tax income | C40: =C33-C39 -> 382.00912 | D40: =D33-D39 -> 451.32196 | E40: =E33-E39 -> 525.75991 | F40: =F33-F39 -> 591.84699 | G40: =G33-G39 -> 661.90303
A41: Income tax | C41: =MAX(C40,0)*'Assumptions'!$B$27 -> 80.221914 | D41: =MAX(D40,0)*'Assumptions'!$B$27 -> 94.777611 | E41: =MAX(E40,0)*'Assumptions'!$B$27 -> 110.40958 | F41: =MAX(F40,0)*'Assumptions'!$B$27 -> 124.28787 | G41: =MAX(G40,0)*'Assumptions'!$B$27 -> 138.99964
A42: Net income | C42: =C40-C41 -> 301.7872 | D42: =D40-D41 -> 356.54435 | E42: =E40-E41 -> 415.35033 | F42: =F40-F41 -> 467.55912 | G42: =G40-G41 -> 522.9034

Sheet DCF
A1: Keystone Freight Lines, Inc. - DCF Valuation
A2: US$ millions unless noted. Unlevered free cash flow, end-of-period discounting.
A4: Discount rate (WACC) | H4: Source / note
A5: Valuation date | B5: =DATE(2026,3,1) -> 46082 | H5: Model date
A6: Equity risk premium | B6: 0.05 | H6: House view
A7: Levered beta | B7: 1.2 | H7: Median of US truckload carrier peers, 2-year weekly
A8: Size premium | B8: 0.01 | H8: House view
A9: Cost of equity | B9: =0.0397+B7*B6+B8 -> 0.1097 | H9: CAPM + size premium
A10: Pre-tax cost of debt | B10: ='P&L'!C38 -> 0.0553 | H10: Equipment note all-in rate, FY2026E
A11: Tax rate | B11: ='Assumptions'!B27 -> 0.21
A12: After-tax cost of debt | B12: =B10*(1-B11) -> 0.043687
A13: Target debt / total capital | B13: 0.35 | H13: Board-approved capital structure
A14: WACC | B14: =B9*(1-B13)+B12*B13 -> 0.08659545
A15: Terminal growth rate | B15: 0.025 | H15: House view, long-run nominal growth
A17: Unlevered free cash flow | C17: FY2026E | D17: FY2027E | E17: FY2028E | F17: FY2029E | G17: FY2030E
A18: Fiscal year end | C18: =DATE(2026,12,31) -> 46387 | D18: =DATE(YEAR(C18)+1,12,31) -> 46752 | E18: =DATE(YEAR(D18)+1,12,31) -> 47118 | F18: =DATE(YEAR(E18)+1,12,31) -> 47483 | G18: =DATE(YEAR(F18)+1,12,31) -> 47848
A19: EBITDA | C19: ='P&L'!C30 -> 683.61649 | D19: ='P&L'!D30 -> 760.97132 | E19: ='P&L'!E30 -> 844.28601 | F19: ='P&L'!F30 -> 917.48711 | G19: ='P&L'!G30 -> 995.30659
A20: Less: depreciation and amortization | C20: =-'P&L'!C32 -> -243.81887 | D20: =-'P&L'!D32 -> -257.94386 | E20: =-'P&L'!E32 -> -272.9036 | F20: =-'P&L'!F32 -> -286.10062 | G20: =-'P&L'!G32 -> -299.94706
A21: EBIT | C21: =C19+C20 -> 439.79762 | D21: =D19+D20 -> 503.02746 | E21: =E19+E20 -> 571.38241 | F21: =F19+F20 -> 631.38649 | G21: =G19+G20 -> 695.35953
A22: Less: taxes on EBIT | C22: =-MAX(C21,0)*$B$11 -> -92.357499 | D22: =-MAX(D21,0)*$B$11 -> -105.63577 | E22: =-MAX(E21,0)*$B$11 -> -119.99031 | F22: =-MAX(F21,0)*$B$11 -> -132.59116 | G22: =-MAX(G21,0)*$B$11 -> -146.0255
A23: Add back: depreciation and amortization | C23: =-C20 -> 243.81887 | D23: =-D20 -> 257.94386 | E23: =-E20 -> 272.9036 | F23: =-F20 -> 286.10062 | G23: =-G20 -> 299.94706
A24: Less: capex | C24: =-'P&L'!C16*'Assumptions'!$B$20 -> -298.00085 | D24: =-'P&L'!D16*'Assumptions'!$B$20 -> -315.26472 | E24: =-'P&L'!E16*'Assumptions'!$B$20 -> -333.54884 | F24: =-'P&L'!F16*'Assumptions'!$B$20 -> -349.67854 | G24: =-'P&L'!G16*'Assumptions'!$B$20 -> -366.60196
A25: Less: increase in net working capital | C25: =-('P&L'!C15-'P&L'!B15)*'Assumptions'!$B$21 -> -0.86238549 | D25: =-('P&L'!D15-'P&L'!C15)*'Assumptions'!$B$21 -> -10.162736 | E25: =-('P&L'!E15-'P&L'!D15)*'Assumptions'!$B$21 -> -10.745347 | F25: =-('P&L'!F15-'P&L'!E15)*'Assumptions'!$B$21 -> -9.4830571 | G25: =-('P&L'!G15-'P&L'!F15)*'Assumptions'!$B$21 -> -9.9365499
A26: Unlevered free cash flow | C26: =SUM(C21:C25) -> 292.39576 | D26: =SUM(D21:D25) -> 329.9081 | E26: =SUM(E21:E25) -> 380.00152 | F26: =SUM(F21:F25) -> 425.73435 | G26: =SUM(G21:G25) -> 472.74258
A27: Share of year after valuation date | C27: =MIN(1,(C18-$B$5)/365) -> 0.83561644 | D27: =MIN(1,(D18-$B$5)/365) -> 1 | E27: =MIN(1,(E18-$B$5)/365) -> 1 | F27: =MIN(1,(F18-$B$5)/365) -> 1 | G27: =MIN(1,(G18-$B$5)/365) -> 1
A28: Free cash flow to discount | C28: =C26*C27 -> 244.3307 | D28: =D26*D27 -> 329.9081 | E28: =E26*E27 -> 380.00152 | F28: =F26*F27 -> 425.73435 | G28: =G26*G27 -> 472.74258
A29: Discount period (years) | C29: =(C18-$B$5)/365 -> 0.83561644 | D29: =(D18-$B$5)/365 -> 1.8356164 | E29: =(E18-$B$5)/365 -> 2.8383562 | F29: =(F18-$B$5)/365 -> 3.8383562 | G29: =(G18-$B$5)/365 -> 4.8383562
A30: Discount factor | C30: =1/(1+$B$14)^C29 -> 0.93295583 | D30: =1/(1+$B$14)^D29 -> 0.85860458 | E30: =1/(1+$B$14)^E29 -> 0.78999893 | F30: =1/(1+$B$14)^F29 -> 0.72704053 | G30: =1/(1+$B$14)^G29 -> 0.66909955
A31: Present value of free cash flow | C31: =C28*C30 -> 227.94975 | D31: =D28*D30 -> 283.2606 | E31: =E28*E30 -> 300.20079 | F31: =F28*F30 -> 309.52613 | G31: =G28*G30 -> 316.31185
A33: Valuation
A34: Sum of PV of free cash flow, FY2026E-FY2030E | B34: =SUM(C31:G31) -> 1437.2491
A35: Terminal value at end of FY2030E (Gordon growth) | B35: =G26*(1+B15)/(B14-B15) -> 7866.8334
A36: PV of terminal value | B36: =B35*G30 -> 5263.6947
A37: Enterprise value (NPV) | B37: =B34+B36 -> 6700.9439
A38: Less: debt outstanding | B38: =-'Assumptions'!B30 -> -1100 | H38: Amortization is paid in December, so the 31-Dec-2025 balance is still outstanding
A39: Add: cash | B39: ='Assumptions'!B33 -> 140
A40: Equity value | B40: =SUM(B37:B39) -> 5740.9439
A41: Implied EV / FY2026E EBITDA | B41: =B37/'P&L'!C30 -> 9.8021975
A42: Terminal value share of enterprise value | B42: =B36/B37 -> 0.78551542
