Workbook

Sheet Cover
B2: Bluestem Coffee Roasters, Inc.
B3: Five-year operating model and DCF valuation
B5: Model date | C5: 46143
B6: Market inputs as of | C6: Close of 30-Apr-2026
B7: Prepared by | C7: FP&A / Corporate Development
B8: Version | C8: v1 - board pre-read, May 2026
B9: Currency / units | C9: US$ millions unless noted
B10: Fiscal year | C10: Calendar year (FY2026 = Jan-Dec 2026)
B12: Business | C12: US roaster of branded and private-label coffee for grocery and foodservice. Buys green arabica priced off the arabica benchmark, about half from its own sourcing and dry-mill operation in Brazil; delivers to stores with its own diesel fleet.
B14: Tabs
B15: Assumptions | C15: Operating, market, policy and financing inputs
B16: P&L | C16: Revenue build, operating costs, EBITDA, interest, net income
B17: DCF | C17: WACC, unlevered free cash flow, NPV / enterprise and equity value
B19: Colour legend
B20: 1,234 | C20: Hardcoded input
B21: 1,234 | C21: Formula
B22: 1,234 | C22: Link to another tab
C23: Key output

Sheet Assumptions
A1: Bluestem Coffee Roasters, Inc. - Assumptions
A2: Model date 1-May-2026. Market inputs at close of 30-Apr-2026. US$ millions unless noted.
A4: Volumes and pricing | B4: Value | C4: Unit | H4: Source / note
A5: FY2025A net revenue | B5: 920 | C5: $mm | H5: FY2025 audited financial statements
A6: Green coffee roasted, FY2026E | B6: 118 | C6: million lbs | H6: 2026 volume plan
A7: Roast shrink (weight loss in roasting) | B7: 0.16 | C7: % | H7: Plant standard
A8: Net price per roasted lb, FY2026E | B8: 9.75 | C8: $/lb | H8: 2026 price list net of trade spend
A9: Contract differential over arabica benchmark | B9: 38 | C9: cents/lb | H9: Weighted 2026 purchase contracts
A10: Brazil-origin share of green purchases | B10: 0.55 | C10: % | H10: 2026 sourcing plan
A11: Brazil sourcing and dry-mill costs, FY2026E | B11: 210 | C11: R$mm | H11: Minas Gerais operation, BRL cost base
A12: Natural gas used in roasting, FY2026E | B12: 420 | C12: 000 MMBtu | H12: Plant energy plan
A13: Utility delivery charge over Henry Hub | B13: 4.5 | C13: $/MMBtu | H13: Utility tariff schedule
A14: Delivery fleet diesel, FY2026E | B14: 6.8 | C14: million gal | H14: Fleet plan
A15: Packaging, % of revenue | B15: 0.07 | C15: % | H15: FY2025A run-rate
A16: Plant labor and overhead, % of revenue | B16: 0.11 | C16: % | H16: FY2025A run-rate
... A20: Net working capital, % of revenue | B20: 0.16 | C20: % | H20: FY2025A actual
A22: Market and policy inputs (close of 30-Apr-2026)
A23: Arabica coffee, other mild arabicas | B23: 334.11 | C23: cents/lb | H23: IMF monthly average for Mar-2026 (latest published), FRED series PCOFFOTMUSDM
A24: Natural gas, Henry Hub spot | B24: 2.64 | C24: $/MMBtu | H24: EIA, FRED series DHHNGSP, 30-Apr-2026
A25: On-highway diesel, US average retail | B25: 5.351 | C25: $/gal | H25: EIA weekly, FRED series GASDESW, week of 27-Apr-2026
A26: Additional US tariff on Brazilian green coffee | B26: 0 | C26: % | H26: Green coffee exempt from the Section 122 surcharge (Annex II)
A27: US federal corporate income tax rate | B27: 0.21 | C27: % | H27: IRC section 11(b)
A29: Financing
A30: Term loan balance, 31-Dec-2025 | B30: 380 | C30: $mm | H30: Credit agreement; amortization paid each December
A31: Scheduled amortization, % of balance per year | B31: 0.05 | C31: % | H31: Credit agreement
A32: SOFR | B32: 0.0366 | C32: % | H32: NY Fed SOFR, FRED series SOFR, 30-Apr-2026
A33: Term loan margin over SOFR | B33: 0.03 | C33: % | H33: Credit agreement
A34: Cash, 30-Apr-2026 | B34: 58 | C34: $mm | H34: Management accounts
A36: Growth | B36: FY2026E | C36: FY2027E | D36: FY2028E | E36: FY2029E | F36: FY2030E
A37: Volume growth, year on year | B37: 0.04 | C37: 0.045 | D37: 0.045 | E37: 0.04 | F37: 0.04 | H37: Management plan
A38: Price growth, year on year | B38: 0.03 | C38: 0.03 | D38: 0.025 | E38: 0.025 | F38: 0.025 | H38: Pricing plan

Sheet P&L
A1: Bluestem Coffee Roasters, Inc. - Income Statement
A2: US$ millions unless noted
B4: FY2025A | C4: FY2026E | D4: FY2027E | E4: FY2028E | F4: FY2029E | G4: FY2030E
A5: Volume growth | C5: ='Assumptions'!B37 -> 0.04 | D5: ='Assumptions'!C37 -> 0.045 | E5: ='Assumptions'!D37 -> 0.045 | F5: ='Assumptions'!E37 -> 0.04 | G5: ='Assumptions'!F37 -> 0.04
A6: Price growth | C6: ='Assumptions'!B38 -> 0.03 | D6: ='Assumptions'!C38 -> 0.03 | E6: ='Assumptions'!D38 -> 0.025 | F6: ='Assumptions'!E38 -> 0.025 | G6: ='Assumptions'!F38 -> 0.025
A7: Green coffee roasted (million lbs) | C7: ='Assumptions'!$B$6 -> 118 | D7: =C7*(1+'Assumptions'!C37) -> 123.31 | E7: =D7*(1+'Assumptions'!D37) -> 128.85895 | F7: =E7*(1+'Assumptions'!E37) -> 134.01331 | G7: =F7*(1+'Assumptions'!F37) -> 139.37384
A8: Roasted coffee sold (million lbs) | C8: =C7*(1-'Assumptions'!$B$7) -> 99.12 | D8: =D7*(1-'Assumptions'!$B$7) -> 103.5804 | E8: =E7*(1-'Assumptions'!$B$7) -> 108.24152 | F8: =F7*(1-'Assumptions'!$B$7) -> 112.57118 | G8: =G7*(1-'Assumptions'!$B$7) -> 117.07403
A9: Net price per roasted lb ($) | C9: ='Assumptions'!$B$8 -> 9.75 | D9: =C9*(1+'Assumptions'!C38) -> 10.0425 | E9: =D9*(1+'Assumptions'!D38) -> 10.293563 | F9: =E9*(1+'Assumptions'!E38) -> 10.550902 | G9: =F9*(1+'Assumptions'!F38) -> 10.814674
A10: Net revenue | B10: ='Assumptions'!B5 -> 920 | C10: =C8*C9 -> 966.42 | D10: =D8*D9 -> 1040.2062 | E10: =E8*E9 -> 1114.1908 | F10: =F8*F9 -> 1187.7274 | G10: =G8*G9 -> 1266.1174
A12: Cost of goods sold
A13: Green coffee | C13: =C7*('Assumptions'!$B$23+'Assumptions'!$B$9)/100 -> 439.0898 | D13: =D7*('Assumptions'!$B$23+'Assumptions'!$B$9)/100 -> 458.84884 | E13: =E7*('Assumptions'!$B$23+'Assumptions'!$B$9)/100 -> 479.49704 | F13: =F7*('Assumptions'!$B$23+'Assumptions'!$B$9)/100 -> 498.67692 | G13: =G7*('Assumptions'!$B$23+'Assumptions'!$B$9)/100 -> 518.624
A14: Import tariffs, Brazil origin | C14: =C13*'Assumptions'!$B$10*'Assumptions'!$B$26 -> 0 | D14: =D13*'Assumptions'!$B$10*'Assumptions'!$B$26 -> 0 | E14: =E13*'Assumptions'!$B$10*'Assumptions'!$B$26 -> 0 | F14: =F13*'Assumptions'!$B$10*'Assumptions'!$B$26 -> 0 | G14: =G13*'Assumptions'!$B$10*'Assumptions'!$B$26 -> 0
A15: Brazil sourcing and dry-mill costs (R$mm) | C15: ='Assumptions'!$B$11 -> 210 | D15: =C15*(1+'Assumptions'!C37) -> 219.45 | E15: =D15*(1+'Assumptions'!D37) -> 229.32525 | F15: =E15*(1+'Assumptions'!E37) -> 238.49826 | G15: =F15*(1+'Assumptions'!F37) -> 248.03819
A16: Brazil sourcing and dry-mill costs | C16: =C15/4.9792 -> 42.17545 | D16: =D15/4.9792 -> 44.073345 | E16: =E15/4.9792 -> 46.056646 | F16: =F15/4.9792 -> 47.898911 | G16: =G15/4.9792 -> 49.814868
A17: Natural gas used (000 MMBtu) | C17: ='Assumptions'!$B$12 -> 420 | D17: =C17*(1+'Assumptions'!C37) -> 438.9 | E17: =D17*(1+'Assumptions'!D37) -> 458.6505 | F17: =E17*(1+'Assumptions'!E37) -> 476.99652 | G17: =F17*(1+'Assumptions'!F37) -> 496.07638
A18: Roasting energy | C18: =C17*('Assumptions'!$B$24+'Assumptions'!$B$13)/1000 -> 2.9988 | D18: =D17*('Assumptions'!$B$24+'Assumptions'!$B$13)/1000 -> 3.133746 | E18: =E17*('Assumptions'!$B$24+'Assumptions'!$B$13)/1000 -> 3.2747646 | F18: =F17*('Assumptions'!$B$24+'Assumptions'!$B$13)/1000 -> 3.4057552 | G18: =G17*('Assumptions'!$B$24+'Assumptions'!$B$13)/1000 -> 3.5419854
A19: Delivery diesel (million gal) | C19: ='Assumptions'!$B$14 -> 6.8 | D19: =C19*(1+'Assumptions'!C37) -> 7.106 | E19: =D19*(1+'Assumptions'!D37) -> 7.42577 | F19: =E19*(1+'Assumptions'!E37) -> 7.7228008 | G19: =F19*(1+'Assumptions'!F37) -> 8.0317128
A20: Delivery fuel | C20: =C19*'Assumptions'!$B$25 -> 36.3868 | D20: =D19*'Assumptions'!$B$25 -> 38.024206 | E20: =E19*'Assumptions'!$B$25 -> 39.735295 | F20: =F19*'Assumptions'!$B$25 -> 41.324707 | G20: =G19*'Assumptions'!$B$25 -> 42.977695
A21: Packaging | C21: =C10*'Assumptions'!$B$15 -> 67.6494 | D21: =D10*'Assumptions'!$B$15 -> 72.814432 | E21: =E10*'Assumptions'!$B$15 -> 77.993358 | F21: =F10*'Assumptions'!$B$15 -> 83.14092 | G21: =G10*'Assumptions'!$B$15 -> 88.62822
A22: Plant labor and overhead | C22: =C10*'Assumptions'!$B$16 -> 106.3062 | D22: =D10*'Assumptions'!$B$16 -> 114.42268 | E22: =E10*'Assumptions'!$B$16 -> 122.56099 | F22: =F10*'Assumptions'!$B$16 -> 130.65002 | G22: =G10*'Assumptions'!$B$16 -> 139.27292
A23: Total cost of goods sold | C23: =C13+C14+C16+C18+C20+C21+C22 -> 694.60645 | D23: =D13+D14+D16+D18+D20+D21+D22 -> 731.31725 | E23: =E13+E14+E16+E18+E20+E21+E22 -> 769.11809 | F23: =F13+F14+F16+F18+F20+F21+F22 -> 805.09723 | G23: =G13+G14+G16+G18+G20+G21+G22 -> 842.85968
A24: Gross profit | C24: =C10-C23 -> 271.81355 | D24: =D10-D23 -> 308.88892 | E24: =E10-E23 -> 345.07274 | F24: =F10-F23 -> 382.63019 | G24: =G10-G23 -> 423.25775
A25: Gross margin | C25: =C24/C10 -> 0.2812582 | D25: =D24/D10 -> 0.29694971 | E25: =E24/E10 -> 0.30970703 | F25: =F24/F10 -> 0.3221532 | G25: =G24/G10 -> 0.33429581
A26: SG&A | C26: =C10*'Assumptions'!$B$17 -> 173.9556 | D26: =D10*'Assumptions'!$B$17 -> 187.23711 | E26: =E10*'Assumptions'!$B$17 -> 200.55435 | F26: =F10*'Assumptions'!$B$17 -> 213.79094 | G26: =G10*'Assumptions'!$B$17 -> 227.90114
A27: EBITDA | C27: =C24-C26 -> 97.85795 | D27: =D24-D26 -> 121.65181 | E27: =E24-E26 -> 144.51839 | F27: =F24-F26 -> 168.83926 | G27: =G24-G26 -> 195.35661
A28: EBITDA margin | C28: =C27/C10 -> 0.1012582 | D28: =D27/D10 -> 0.11694971 | E28: =E27/E10 -> 0.12970703 | F28: =F27/F10 -> 0.1421532 | G28: =G27/G10 -> 0.15429581
A29: Depreciation and amortization | C29: =C10*'Assumptions'!$B$18 -> 24.1605 | D29: =D10*'Assumptions'!$B$18 -> 26.005154 | E29: =E10*'Assumptions'!$B$18 -> 27.854771 | F29: =F10*'Assumptions'!$B$18 -> 29.693186 | G29: =G10*'Assumptions'!$B$18 -> 31.652936
A30: EBIT | C30: =C27-C29 -> 73.69745 | D30: =D27-D29 -> 95.646655 | E30: =E27-E29 -> 116.66362 | F30: =F27-F29 -> 139.14607 | G30: =G27-G29 -> 163.70368
A32: Financing
A33: Debt, opening | C33: ='Assumptions'!$B$30 -> 380 | D33: =C34 -> 361 | E33: =D34 -> 342 | F33: =E34 -> 323 | G33: =F34 -> 304
A34: Debt, closing | C34: =MAX(C33-'Assumptions'!$B$30*'Assumptions'!$B$31,0) -> 361 | D34: =MAX(D33-'Assumptions'!$B$30*'Assumptions'!$B$31,0) -> 342 | E34: =MAX(E33-'Assumptions'!$B$30*'Assumptions'!$B$31,0) -> 323 | F34: =MAX(F33-'Assumptions'!$B$30*'Assumptions'!$B$31,0) -> 304 | G34: =MAX(G33-'Assumptions'!$B$30*'Assumptions'!$B$31,0) -> 285
A35: Interest rate (SOFR + margin) | C35: ='Assumptions'!$B$32+'Assumptions'!$B$33 -> 0.0666 | D35: ='Assumptions'!$B$32+'Assumptions'!$B$33 -> 0.0666 | E35: ='Assumptions'!$B$32+'Assumptions'!$B$33 -> 0.0666 | F35: ='Assumptions'!$B$32+'Assumptions'!$B$33 -> 0.0666 | G35: ='Assumptions'!$B$32+'Assumptions'!$B$33 -> 0.0666
A36: Interest expense | C36: =AVERAGE(C33,C34)*C35 -> 24.6753 | D36: =AVERAGE(D33,D34)*D35 -> 23.4099 | E36: =AVERAGE(E33,E34)*E35 -> 22.1445 | F36: =AVERAGE(F33,F34)*F35 -> 20.8791 | G36: =AVERAGE(G33,G34)*G35 -> 19.6137
A37: Pre-tax income | C37: =C30-C36 -> 49.02215 | D37: =D30-D36 -> 72.236755 | E37: =E30-E36 -> 94.519117 | F37: =F30-F36 -> 118.26697 | G37: =G30-G36 -> 144.08998
A38: Income tax | C38: =MAX(C37,0)*'Assumptions'!$B$27 -> 10.294652 | D38: =MAX(D37,0)*'Assumptions'!$B$27 -> 15.169718 | E38: =MAX(E37,0)*'Assumptions'!$B$27 -> 19.849014 | F38: =MAX(F37,0)*'Assumptions'!$B$27 -> 24.836064 | G38: =MAX(G37,0)*'Assumptions'!$B$27 -> 30.258895
A39: Net income | C39: =C37-C38 -> 38.727499 | D39: =D37-D38 -> 57.067036 | E39: =E37-E38 -> 74.670102 | F39: =F37-F38 -> 93.430908 | G39: =G37-G38 -> 113.83108

Sheet DCF
A1: Bluestem Coffee Roasters, Inc. - DCF Valuation
A2: US$ millions unless noted. Unlevered free cash flow, end-of-period discounting.
A4: Discount rate (WACC) | H4: Source / note
A5: Valuation date | B5: =DATE(2026,5,1) -> 46143 | H5: Model date
A6: Risk-free rate (10-year US Treasury) | B6: 0.044 | H6: FRED series DGS10, 30-Apr-2026
A7: Equity risk premium | B7: 0.05 | H7: House view
A8: Levered beta | B8: 0.95 | H8: Median of packaged coffee and beverage peers, 2-year weekly
A9: Size premium | B9: 0.015 | H9: House view
A10: Cost of equity | B10: =B6+B8*B7+B9 -> 0.1065 | H10: CAPM + size premium
A11: Pre-tax cost of debt | B11: ='P&L'!C35 -> 0.0666 | H11: Term loan all-in rate, FY2026E
A12: Tax rate | B12: ='Assumptions'!B27 -> 0.21
A13: After-tax cost of debt | B13: =B11*(1-B12) -> 0.052614
A14: Target debt / total capital | B14: 0.3 | H14: Board-approved capital structure
A15: WACC | B15: =B10*(1-B14)+B13*B14 -> 0.0903342
A16: Terminal growth rate | B16: 0.025 | H16: House view, long-run nominal growth
A18: Unlevered free cash flow | C18: FY2026E | D18: FY2027E | E18: FY2028E | F18: FY2029E | G18: FY2030E
A19: Fiscal year end | C19: =DATE(2026,12,31) -> 46387 | D19: =DATE(YEAR(C19)+1,12,31) -> 46752 | E19: =DATE(YEAR(D19)+1,12,31) -> 47118 | F19: =DATE(YEAR(E19)+1,12,31) -> 47483 | G19: =DATE(YEAR(F19)+1,12,31) -> 47848
A20: EBITDA | C20: ='P&L'!C27 -> 97.85795 | D20: ='P&L'!D27 -> 121.65181 | E20: ='P&L'!E27 -> 144.51839 | F20: ='P&L'!F27 -> 168.83926 | G20: ='P&L'!G27 -> 195.35661
A21: Less: depreciation and amortization | C21: =-'P&L'!C29 -> -24.1605 | D21: =-'P&L'!D29 -> -26.005154 | E21: =-'P&L'!E29 -> -27.854771 | F21: =-'P&L'!F29 -> -29.693186 | G21: =-'P&L'!G29 -> -31.652936
A22: EBIT | C22: =C20+C21 -> 73.69745 | D22: =D20+D21 -> 95.646655 | E22: =E20+E21 -> 116.66362 | F22: =F20+F21 -> 139.14607 | G22: =G20+G21 -> 163.70368
A23: Less: taxes on EBIT | C23: =-MAX(C22,0)*$B$12 -> -15.476465 | D23: =-MAX(D22,0)*$B$12 -> -20.085797 | E23: =-MAX(E22,0)*$B$12 -> -24.499359 | F23: =-MAX(F22,0)*$B$12 -> -29.220675 | G23: =-MAX(G22,0)*$B$12 -> -34.377772
A24: Add back: depreciation and amortization | C24: =-C21 -> 24.1605 | D24: =-D21 -> 26.005154 | E24: =-E21 -> 27.854771 | F24: =-F21 -> 29.693186 | G24: =-G21 -> 31.652936
A25: Less: capex | C25: =-'P&L'!C10*'Assumptions'!$B$19 -> -28.9926 | D25: =-'P&L'!D10*'Assumptions'!$B$19 -> -31.206185 | E25: =-'P&L'!E10*'Assumptions'!$B$19 -> -33.425725 | F25: =-'P&L'!F10*'Assumptions'!$B$19 -> -35.631823 | G25: =-'P&L'!G10*'Assumptions'!$B$19 -> -37.983523
A26: Less: increase in net working capital | C26: =-('P&L'!C10-'P&L'!B10)*'Assumptions'!$B$20 -> -7.4272 | D26: =-('P&L'!D10-'P&L'!C10)*'Assumptions'!$B$20 -> -11.805787 | E26: =-('P&L'!E10-'P&L'!D10)*'Assumptions'!$B$20 -> -11.837546 | F26: =-('P&L'!F10-'P&L'!E10)*'Assumptions'!$B$20 -> -11.765855 | G26: =-('P&L'!G10-'P&L'!F10)*'Assumptions'!$B$20 -> -12.542402
A27: Unlevered free cash flow | C27: =SUM(C22:C26) -> 45.961686 | D27: =SUM(D22:D26) -> 58.55404 | E27: =SUM(E22:E26) -> 74.755757 | F27: =SUM(F22:F26) -> 92.220905 | G27: =SUM(G22:G26) -> 110.45292
A28: Share of year after valuation date | C28: =MIN(1,(C19-$B$5)/365) -> 0.66849315 | D28: =MIN(1,(D19-$B$5)/365) -> 1 | E28: =MIN(1,(E19-$B$5)/365) -> 1 | F28: =MIN(1,(F19-$B$5)/365) -> 1 | G28: =MIN(1,(G19-$B$5)/365) -> 1
A29: Free cash flow to discount | C29: =C27*C28 -> 30.725072 | D29: =D27*D28 -> 58.55404 | E29: =E27*E28 -> 74.755757 | F29: =F27*F28 -> 92.220905 | G29: =G27*G28 -> 110.45292
A30: Discount period (years) | C30: =(C19-$B$5)/365 -> 0.66849315 | D30: =(D19-$B$5)/365 -> 1.6684932 | E30: =(E19-$B$5)/365 -> 2.6712329 | F30: =(F19-$B$5)/365 -> 3.6712329 | G30: =(G19-$B$5)/365 -> 4.6712329
A31: Discount factor | C31: =1/(1+$B$15)^C30 -> 0.94382536 | D31: =1/(1+$B$15)^D30 -> 0.86562942 | E31: =1/(1+$B$15)^E30 -> 0.79372392 | F31: =1/(1+$B$15)^F30 -> 0.72796389 | G31: =1/(1+$B$15)^G30 -> 0.66765207
A32: Present value of free cash flow | C32: =C29*C31 -> 28.999102 | D32: =D29*D31 -> 50.686099 | E32: =E29*E31 -> 59.335432 | F32: =F29*F31 -> 67.133488 | G32: =G29*G31 -> 73.744118
A34: Valuation
A35: Sum of PV of free cash flow, FY2026E-FY2030E | B35: =SUM(C32:G32) -> 279.89824
A36: Terminal value at end of FY2030E (Gordon growth) | B36: =G27*(1+B16)/(B15-B16) -> 1732.848
A37: PV of terminal value | B37: =B36*G31 -> 1156.9396
A38: Enterprise value (NPV) | B38: =B35+B37 -> 1436.8378
A39: Less: debt outstanding | B39: =-'Assumptions'!B30 -> -380 | H39: Amortization is paid in December, so the 31-Dec-2025 balance is still outstanding
A40: Add: cash | B40: ='Assumptions'!B34 -> 58
A41: Equity value | B41: =SUM(B38:B40) -> 1114.8378
A42: Implied EV / FY2026E EBITDA | B42: =B38/'P&L'!C27 -> 14.682893
A43: Terminal value share of enterprise value | B43: =B37/B38 -> 0.80519844
