Workbook

Sheet Cover
B2: Calder & Finch Home, Inc.
B3: Five-year operating model and DCF valuation
B5: Model date | C5: 46235
B6: Market inputs as of | C6: Close of 31-Jul-2026
B7: Prepared by | C7: FP&A / Corporate Development
B8: Version | C8: v3 - board pre-read, August 2026
B9: Currency / units | C9: US$ millions unless noted
B10: Fiscal year | C10: Calendar year (FY2026 = Jan-Dec 2026)
B12: Business | C12: US designer and wholesaler of residential furniture (seating, casegoods, outdoor). Sources from Vietnam, Canada, the EU and US domestic plants; sells to retailers and DTC.
B14: Tabs
B15: Assumptions | C15: Operating, market, policy and financing inputs
B16: P&L | C16: Revenue build, cost of goods, EBITDA, interest, net income
B17: DCF | C17: WACC, unlevered free cash flow, NPV / enterprise and equity value
B19: Colour legend
B20: 1,234 | C20: Hardcoded input
B21: 1,234 | C21: Formula
B22: 1,234 | C22: Link to another tab
C23: Key output

Sheet Assumptions
A1: Calder & Finch Home, Inc. - Assumptions
A2: Model date 1-Aug-2026. Market inputs at close of 31-Jul-2026. US$ millions unless noted.
A4: Revenue and cost structure | B4: Value | C4: Unit | H4: Source / note
A5: FY2025A net revenue | B5: 812 | C5: $mm | H5: FY2025 audited financial statements
A6: Purchases from non-EU suppliers, % of revenue | B6: 0.38 | C6: % | H6: FY2025A actual mix
A7: of which Vietnam | B7: 0.5 | C7: % of non-EU | H7: 2026 sourcing plan
A8: of which Canada | B8: 0.3 | C8: % of non-EU | H8: 2026 sourcing plan (Quebec and Ontario plants)
A9: of which US domestic | B9: =1-B7-B8 -> 0.2 | C9: % of non-EU | H9: Balance
A10: EU supplier contract volume, FY2026E | B10: 74 | C10: €mm | H10: 2026 supplier contracts, priced in EUR (Italy, Portugal)
A11: Containers imported from Asia, FY2026E | B11: 9800 | C11: FEU | H11: 2026 logistics plan (40ft equivalent units)
A12: Oil-linked consumption, FY2026E | B12: 420 | C12: 000 bbl-eq | H12: Procurement estimate: foam, poly, packaging, diesel
A13: SG&A, % of revenue | B13: 0.19 | C13: % | H13: FY2025A run-rate
A14: Warehousing and distribution, % of revenue | B14: 0.065 | C14: % | H14: FY2025A run-rate
A15: D&A, % of revenue | B15: 0.022 | C15: % | H15: FY2025A run-rate
A16: Capex, % of revenue | B16: 0.025 | C16: % | H16: Five-year capital plan
A17: Net working capital, % of revenue | B17: 0.14 | C17: % | H17: FY2025A actual
A19: Market and policy inputs (close of 31-Jul-2026)
A20: Brent crude oil | B20: 96.95 | C20: $/bbl | H20: EIA Europe Brent spot, FRED series DCOILBRENTEU, 31-Jul-2026
A21: EUR/USD exchange rate | B21: 1.1519 | C21: $ per € | H21: Fed H.10 noon buying rate, FRED series DEXUSEU, 31-Jul-2026
A22: Tariff on Vietnam-origin furniture | B22: 0.125 | C22: % | H22: USTR Section 301 forced-labor action, in force 24-Jul-2026
A23: Tariff on Canada-origin furniture | B23: 0 | C23: % | H23: USMCA-qualifying goods enter duty-free
A24: US federal corporate income tax rate | B24: 0.21 | C24: % | H24: IRC section 11(b)
A26: Financing
A27: Term loan balance, 31-Dec-2025 | B27: 300 | C27: $mm | H27: Credit agreement dated 14-Mar-2024; amortization paid each December
A28: Scheduled amortization, % of original balance per year | B28: 0.05 | C28: % | H28: Credit agreement
A29: Term loan margin over SOFR | B29: 0.0275 | C29: % | H29: Credit agreement, current leverage grid
A30: Cash, 31-Jul-2026 | B30: 46 | C30: $mm | H30: July 2026 management accounts
A32: Revenue growth | B32: FY2026E | C32: FY2027E | D32: FY2028E | E32: FY2029E | F32: FY2030E
A33: Net revenue growth, year on year | B33: 0.04 | C33: 0.045 | D33: 0.045 | E33: 0.04 | F33: 0.035 | H33: Management plan, June 2026

Sheet P&L
A1: Calder & Finch Home, Inc. - Income Statement
A2: US$ millions unless noted
B4: FY2025A | C4: FY2026E | D4: FY2027E | E4: FY2028E | F4: FY2029E | G4: FY2030E
A5: Revenue growth | C5: ='Assumptions'!B33 -> 0.04 | D5: ='Assumptions'!C33 -> 0.045 | E5: ='Assumptions'!D33 -> 0.045 | F5: ='Assumptions'!E33 -> 0.04 | G5: ='Assumptions'!F33 -> 0.035
A6: Net revenue | B6: ='Assumptions'!B5 -> 812 | C6: =B6*(1+C5) -> 844.48 | D6: =C6*(1+D5) -> 882.4816 | E6: =D6*(1+E5) -> 922.19327 | F6: =E6*(1+F5) -> 959.081 | G6: =F6*(1+G5) -> 992.64884
A8: Cost of goods sold
A9: Purchases, non-EU suppliers | C9: =C6*'Assumptions'!$B$6 -> 320.9024 | D9: =D6*'Assumptions'!$B$6 -> 335.34301 | E9: =E6*'Assumptions'!$B$6 -> 350.43344 | F9: =F6*'Assumptions'!$B$6 -> 364.45078 | G9: =G6*'Assumptions'!$B$6 -> 377.20656
A10: Vietnam | C10: =C9*'Assumptions'!$B$7 -> 160.4512 | D10: =D9*'Assumptions'!$B$7 -> 167.6715 | E10: =E9*'Assumptions'!$B$7 -> 175.21672 | F10: =F9*'Assumptions'!$B$7 -> 182.22539 | G10: =G9*'Assumptions'!$B$7 -> 188.60328
A11: Canada | C11: =C9*'Assumptions'!$B$8 -> 96.27072 | D11: =D9*'Assumptions'!$B$8 -> 100.6029 | E11: =E9*'Assumptions'!$B$8 -> 105.13003 | F11: =F9*'Assumptions'!$B$8 -> 109.33523 | G11: =G9*'Assumptions'!$B$8 -> 113.16197
A12: US domestic | C12: =C9*'Assumptions'!$B$9 -> 64.18048 | D12: =D9*'Assumptions'!$B$9 -> 67.068602 | E12: =E9*'Assumptions'!$B$9 -> 70.086689 | F12: =F9*'Assumptions'!$B$9 -> 72.890156 | G12: =G9*'Assumptions'!$B$9 -> 75.441312
A13: EU purchases (€mm) | C13: ='Assumptions'!$B$10 -> 74 | D13: =C13*(1+D5) -> 77.33 | E13: =D13*(1+E5) -> 80.80985 | F13: =E13*(1+F5) -> 84.042244 | G13: =F13*(1+G5) -> 86.983723
A14: EU purchases ($mm) | C14: =C13*'Assumptions'!$B$21 -> 85.2406 | D14: =D13*'Assumptions'!$B$21 -> 89.076427 | E14: =E13*'Assumptions'!$B$21 -> 93.084866 | F14: =F13*'Assumptions'!$B$21 -> 96.808261 | G14: =G13*'Assumptions'!$B$21 -> 100.19655
A15: Import tariffs, Vietnam | C15: =C10*'Assumptions'!$B$22 -> 20.0564 | D15: =D10*'Assumptions'!$B$22 -> 20.958938 | E15: =E10*'Assumptions'!$B$22 -> 21.90209 | F15: =F10*'Assumptions'!$B$22 -> 22.778174 | G15: =G10*'Assumptions'!$B$22 -> 23.57541
A16: Import tariffs, Canada | C16: =C11*'Assumptions'!$B$23 -> 0 | D16: =D11*'Assumptions'!$B$23 -> 0 | E16: =E11*'Assumptions'!$B$23 -> 0 | F16: =F11*'Assumptions'!$B$23 -> 0 | G16: =G11*'Assumptions'!$B$23 -> 0
A17: Containers imported (FEU) | C17: ='Assumptions'!$B$11 -> 9800 | D17: =C17*(1+D5) -> 10241 | E17: =D17*(1+E5) -> 10701.845 | F17: =E17*(1+F5) -> 11129.919 | G17: =F17*(1+G5) -> 11519.466
A18: Ocean freight, Asia to US West Coast | C18: =C17*5739/1000000 -> 56.2422 | D18: =D17*5739/1000000 -> 58.773099 | E18: =E17*5739/1000000 -> 61.417888 | F18: =F17*5739/1000000 -> 63.874604 | G18: =G17*5739/1000000 -> 66.110215
A19: Oil-linked consumption (000 bbl-eq) | C19: ='Assumptions'!$B$12 -> 420 | D19: =C19*(1+D5) -> 438.9 | E19: =D19*(1+E5) -> 458.6505 | F19: =E19*(1+F5) -> 476.99652 | G19: =F19*(1+G5) -> 493.6914
A20: Oil-linked materials and fuel | C20: =C19*'Assumptions'!$B$20/1000 -> 40.719 | D20: =D19*'Assumptions'!$B$20/1000 -> 42.551355 | E20: =E19*'Assumptions'!$B$20/1000 -> 44.466166 | F20: =F19*'Assumptions'!$B$20/1000 -> 46.244813 | G20: =G19*'Assumptions'!$B$20/1000 -> 47.863381
A21: Total cost of goods sold | C21: =C9+C14+C15+C16+C18+C20 -> 523.1606 | D21: =D9+D14+D15+D16+D18+D20 -> 546.70283 | E21: =E9+E14+E15+E16+E18+E20 -> 571.30445 | F21: =F9+F14+F15+F16+F18+F20 -> 594.15663 | G21: =G9+G14+G15+G16+G18+G20 -> 614.95211
A22: Gross profit | C22: =C6-C21 -> 321.3194 | D22: =D6-D21 -> 335.77877 | E22: =E6-E21 -> 350.88882 | F22: =F6-F21 -> 364.92437 | G22: =G6-G21 -> 377.69672
A23: Gross margin | C23: =C22/C6 -> 0.38049379 | D23: =D22/D6 -> 0.38049379 | E23: =E22/E6 -> 0.38049379 | F23: =F22/F6 -> 0.38049379 | G23: =G22/G6 -> 0.38049379
A25: SG&A | C25: =C6*'Assumptions'!$B$13 -> 160.4512 | D25: =D6*'Assumptions'!$B$13 -> 167.6715 | E25: =E6*'Assumptions'!$B$13 -> 175.21672 | F25: =F6*'Assumptions'!$B$13 -> 182.22539 | G25: =G6*'Assumptions'!$B$13 -> 188.60328
A26: Warehousing and distribution | C26: =C6*'Assumptions'!$B$14 -> 54.8912 | D26: =D6*'Assumptions'!$B$14 -> 57.361304 | E26: =E6*'Assumptions'!$B$14 -> 59.942563 | F26: =F6*'Assumptions'!$B$14 -> 62.340265 | G26: =G6*'Assumptions'!$B$14 -> 64.522174
A27: EBITDA | C27: =C22-C25-C26 -> 105.977 | D27: =D22-D25-D26 -> 110.74596 | E27: =E22-E25-E26 -> 115.72953 | F27: =F22-F25-F26 -> 120.35871 | G27: =G22-G25-G26 -> 124.57127
A28: EBITDA margin | C28: =C27/C6 -> 0.12549379 | D28: =D27/D6 -> 0.12549379 | E28: =E27/E6 -> 0.12549379 | F28: =F27/F6 -> 0.12549379 | G28: =G27/G6 -> 0.12549379
A29: Depreciation and amortization | C29: =C6*'Assumptions'!$B$15 -> 18.57856 | D29: =D6*'Assumptions'!$B$15 -> 19.414595 | E29: =E6*'Assumptions'!$B$15 -> 20.288252 | F29: =F6*'Assumptions'!$B$15 -> 21.099782 | G29: =G6*'Assumptions'!$B$15 -> 21.838274
A30: EBIT | C30: =C27-C29 -> 87.39844 | D30: =D27-D29 -> 91.33137 | E30: =E27-E29 -> 95.441281 | F30: =F27-F29 -> 99.258933 | G30: =G27-G29 -> 102.733
A32: Financing
A33: Term loan, opening | C33: ='Assumptions'!$B$27 -> 300 | D33: =C34 -> 285 | E33: =D34 -> 270 | F33: =E34 -> 255 | G33: =F34 -> 240
A34: Term loan, closing | C34: =MAX(C33-'Assumptions'!$B$27*'Assumptions'!$B$28,0) -> 285 | D34: =MAX(D33-'Assumptions'!$B$27*'Assumptions'!$B$28,0) -> 270 | E34: =MAX(E33-'Assumptions'!$B$27*'Assumptions'!$B$28,0) -> 255 | F34: =MAX(F33-'Assumptions'!$B$27*'Assumptions'!$B$28,0) -> 240 | G34: =MAX(G33-'Assumptions'!$B$27*'Assumptions'!$B$28,0) -> 225
A35: Interest rate (SOFR + margin) | C35: =0.0366+'Assumptions'!$B$29 -> 0.0641 | D35: =0.0366+'Assumptions'!$B$29 -> 0.0641 | E35: =0.0366+'Assumptions'!$B$29 -> 0.0641 | F35: =0.0366+'Assumptions'!$B$29 -> 0.0641 | G35: =0.0366+'Assumptions'!$B$29 -> 0.0641
A36: Interest expense | C36: =AVERAGE(C33,C34)*C35 -> 18.74925 | D36: =AVERAGE(D33,D34)*D35 -> 17.78775 | E36: =AVERAGE(E33,E34)*E35 -> 16.82625 | F36: =AVERAGE(F33,F34)*F35 -> 15.86475 | G36: =AVERAGE(G33,G34)*G35 -> 14.90325
A37: Pre-tax income | C37: =C30-C36 -> 68.64919 | D37: =D30-D36 -> 73.54362 | E37: =E30-E36 -> 78.615031 | F37: =F30-F36 -> 83.394183 | G37: =G30-G36 -> 87.829745
A38: Income tax | C38: =MAX(C37,0)*'Assumptions'!$B$24 -> 14.41633 | D38: =MAX(D37,0)*'Assumptions'!$B$24 -> 15.44416 | E38: =MAX(E37,0)*'Assumptions'!$B$24 -> 16.509157 | F38: =MAX(F37,0)*'Assumptions'!$B$24 -> 17.512778 | G38: =MAX(G37,0)*'Assumptions'!$B$24 -> 18.444247
A39: Net income | C39: =C37-C38 -> 54.23286 | D39: =D37-D38 -> 58.09946 | E39: =E37-E38 -> 62.105875 | F39: =F37-F38 -> 65.881404 | G39: =G37-G38 -> 69.385499

Sheet DCF
A1: Calder & Finch Home, Inc. - DCF Valuation
A2: US$ millions unless noted. Unlevered free cash flow, end-of-period discounting.
A4: Discount rate (WACC) | H4: Source / note
A5: Valuation date | B5: =DATE(2026,8,1) -> 46235 | H5: Model date
A6: Risk-free rate (10-year US Treasury) | B6: 0.0475 | H6: FRED series DGS10, 31-Jul-2026
A7: Equity risk premium | B7: 0.05 | H7: House view
A8: Levered beta | B8: 1.15 | H8: Median of listed furniture peers, 2-year weekly
A9: Size premium | B9: 0.01 | H9: House view
A10: Cost of equity | B10: =B6+B8*B7+B9 -> 0.115 | H10: CAPM + size premium
A11: Pre-tax cost of debt | B11: ='P&L'!C35 -> 0.0641 | H11: Term loan all-in rate, FY2026E
A12: Tax rate | B12: ='Assumptions'!B24 -> 0.21
A13: After-tax cost of debt | B13: =B11*(1-B12) -> 0.050639
A14: Target debt / total capital | B14: 0.25 | H14: Board-approved capital structure
A15: WACC | B15: =B10*(1-B14)+B13*B14 -> 0.09890975
A16: Terminal growth rate | B16: 0.025 | H16: House view, long-run nominal growth
A18: Unlevered free cash flow | C18: FY2026E | D18: FY2027E | E18: FY2028E | F18: FY2029E | G18: FY2030E
A19: Fiscal year end | C19: =DATE(2026,12,31) -> 46387 | D19: =DATE(YEAR(C19)+1,12,31) -> 46752 | E19: =DATE(YEAR(D19)+1,12,31) -> 47118 | F19: =DATE(YEAR(E19)+1,12,31) -> 47483 | G19: =DATE(YEAR(F19)+1,12,31) -> 47848
A20: EBITDA | C20: ='P&L'!C27 -> 105.977 | D20: ='P&L'!D27 -> 110.74596 | E20: ='P&L'!E27 -> 115.72953 | F20: ='P&L'!F27 -> 120.35871 | G20: ='P&L'!G27 -> 124.57127
A21: Less: depreciation and amortization | C21: =-'P&L'!C29 -> -18.57856 | D21: =-'P&L'!D29 -> -19.414595 | E21: =-'P&L'!E29 -> -20.288252 | F21: =-'P&L'!F29 -> -21.099782 | G21: =-'P&L'!G29 -> -21.838274
A22: EBIT | C22: =C20+C21 -> 87.39844 | D22: =D20+D21 -> 91.33137 | E22: =E20+E21 -> 95.441281 | F22: =F20+F21 -> 99.258933 | G22: =G20+G21 -> 102.733
A23: Less: taxes on EBIT | C23: =-MAX(C22,0)*$B$12 -> -18.353672 | D23: =-MAX(D22,0)*$B$12 -> -19.179588 | E23: =-MAX(E22,0)*$B$12 -> -20.042669 | F23: =-MAX(F22,0)*$B$12 -> -20.844376 | G23: =-MAX(G22,0)*$B$12 -> -21.573929
A24: Add back: depreciation and amortization | C24: =-C21 -> 18.57856 | D24: =-D21 -> 19.414595 | E24: =-E21 -> 20.288252 | F24: =-F21 -> 21.099782 | G24: =-G21 -> 21.838274
A25: Less: capex | C25: =-'P&L'!C6*'Assumptions'!$B$16 -> -21.112 | D25: =-'P&L'!D6*'Assumptions'!$B$16 -> -22.06204 | E25: =-'P&L'!E6*'Assumptions'!$B$16 -> -23.054832 | F25: =-'P&L'!F6*'Assumptions'!$B$16 -> -23.977025 | G25: =-'P&L'!G6*'Assumptions'!$B$16 -> -24.816221
A26: Less: increase in net working capital | C26: =-('P&L'!C6-'P&L'!B6)*'Assumptions'!$B$17 -> -4.5472 | D26: =-('P&L'!D6-'P&L'!C6)*'Assumptions'!$B$17 -> -5.320224 | E26: =-('P&L'!E6-'P&L'!D6)*'Assumptions'!$B$17 -> -5.5596341 | F26: =-('P&L'!F6-'P&L'!E6)*'Assumptions'!$B$17 -> -5.1642823 | G26: =-('P&L'!G6-'P&L'!F6)*'Assumptions'!$B$17 -> -4.6994969
A27: Unlevered free cash flow | C27: =SUM(C22:C26) -> 61.964128 | D27: =SUM(D22:D26) -> 64.184113 | E27: =SUM(E22:E26) -> 67.072398 | F27: =SUM(F22:F26) -> 70.373032 | G27: =SUM(G22:G26) -> 73.481623
A28: Share of year after valuation date | C28: =MIN(1,(C19-$B$5)/365) -> 0.41643836 | D28: =MIN(1,(D19-$B$5)/365) -> 1 | E28: =MIN(1,(E19-$B$5)/365) -> 1 | F28: =MIN(1,(F19-$B$5)/365) -> 1 | G28: =MIN(1,(G19-$B$5)/365) -> 1
A29: Free cash flow to discount | C29: =C27*C28 -> 25.804239 | D29: =D27*D28 -> 64.184113 | E29: =E27*E28 -> 67.072398 | F29: =F27*F28 -> 70.373032 | G29: =G27*G28 -> 73.481623
A30: Discount period (years) | C30: =(C19-$B$5)/365 -> 0.41643836 | D30: =(D19-$B$5)/365 -> 1.4164384 | E30: =(E19-$B$5)/365 -> 2.4191781 | F30: =(F19-$B$5)/365 -> 3.4191781 | G30: =(G19-$B$5)/365 -> 4.4191781
A31: Discount factor | C31: =1/(1+$B$15)^C30 -> 0.96148351 | D31: =1/(1+$B$15)^D30 -> 0.87494311 | E31: =1/(1+$B$15)^E30 -> 0.79598624 | F31: =1/(1+$B$15)^F30 -> 0.72434178 | G31: =1/(1+$B$15)^G30 -> 0.65914583
A32: Present value of free cash flow | C32: =C29*C31 -> 24.810351 | D32: =D29*D31 -> 56.157448 | E32: =E29*E31 -> 53.388707 | F32: =F29*F31 -> 50.974127 | G32: =G29*G31 -> 48.435105
A34: Valuation
A35: Sum of PV of free cash flow, FY2026E-FY2030E | B35: =SUM(C32:G32) -> 233.76574
A36: Terminal value at end of FY2030E (Gordon growth) | B36: =G27*(1+B16)/(B15-B16) -> 1019.0626
A37: PV of terminal value | B37: =B36*G31 -> 671.71088
A38: Enterprise value (NPV) | B38: =B35+B37 -> 905.47661
A39: Less: term loan outstanding | B39: =-'Assumptions'!B27 -> -300 | H39: Amortization is paid in December, so the 31-Dec-2025 balance is still outstanding
A40: Add: cash | B40: ='Assumptions'!B30 -> 46
A41: Equity value | B41: =SUM(B38:B40) -> 651.47661
A42: Implied EV / FY2026E EBITDA | B42: =B38/'P&L'!C27 -> 8.5440861
A43: Terminal value share of enterprise value | B43: =B37/B38 -> 0.74183128
