Workbook

Sheet README
A1: Drift mock dataset: Meridian Rent-A-Car fleet model (Hertz-calibrated)
A3: What this is | B3: A synthetic FP&A workbook for testing Drift. The company is fictional ('Meridian Rent-A-Car'). Its scale and the size of its stale assumptions are calibrated to Hertz's public EV fleet write-down (8-K filed 2024-01-11; Q4 2023 results 2024-02-06).
A4: The story | B4: Model built 2022-12-15 as the FY2023 budget. Rolled forward unchanged to FY2024E and reused 2023-12-04 for a lender update. Between those dates Tesla cut new-car prices repeatedly, used EV values fell, fleet debt got more expensive and EV collision costs stayed high.
A5: Test flow | B5: 1) Feed Inputs + Fleet_Model to Drift. 2) Check it finds every hardcode (Inputs sheet AND the buried constants listed in Driver_Map). 3) Check its driver labels against Driver_Map col B. 4) Check fetched values against Driver_Map col I. 5) Check the impact ranking against Driver_Map col N.
A6: Sheets | B6: Case_Facts: dated, sourced real-world timeline. Inputs: explicit assumptions. Fleet_Model: the model (formulas; three constants are buried inside formulas on purpose). Market_Data: monthly drivers + source anchors. Driver_Map: GROUND TRUTH answer key (label, source, should-it-drift, stale flag, $ impact). Impact_Engine: re-runs the model one driver at a time. Hertz_Reconciliation: reproduces Hertz's $245M from its own disclosed numbers.
A7: Colour code | B7: Blue = hardcoded input. Black = formula. Green = link to another sheet. Yellow fill = key assumption that drifts.
A8: IMPORTANT: data provenance | B8: Market_Data monthly series (EV index, ICE index, SOFR) are SYNTHETIC illustrative paths. Only the Anchors table and Case_Facts hold figures taken from public sources, and each is marked Verified or Mock. Replace the synthetic series with live fetched data when Drift is wired to Bright Data.
A9: Deliberate traps | B9: (a) Fleet_Model B11 contains a buried 1.2 (EV collision cost uplift) that DOES drift. (b) Fleet_Model B13/C13 contain a buried 0.015 (remarketing fee) that has NOT drifted: a fresh control. (c) 365, 12 and 1,000,000 are unit constants, not assumptions. (d) EV and ICE acquisition cost are historical facts and should never be 'updated'. (e) Revenue per day is a management lever: label it, do not auto-update it.
A10: Units | B10: $M unless stated. Annual FY2024E view. Fleet = 550,000 vehicles (60,000 EV = about one third of Hertz's disclosed EV fleet after the 20,000 sale decision).

Sheet Case_Facts
A1: Hertz EV case: dated facts (paraphrased from sources)
A3: Date | B3: Fact | C3: Why it matters for Drift | D3: Source
A4: 2021-10 | B4: Hertz announces an order of up to 100,000 Teslas, reported at about $4.2B (about $42,000 per car). | C4: Sets the historical cost basis. This is a fact, not an assumption, so Drift must NOT try to update it. | D4: Fortune, 2024-06-07: https://fortune.com/2024/06/07/buy-used-tesla-hertz-fire-sale
A5: 2022 | B5: Hertz announces plans to buy 165,000 EVs from Tesla and Polestar. | C5: Fleet plan was sized on EV demand and residual assumptions of the time. | D5: Axios, 2024-01-11: https://www.axios.com/2024/01/11/hertz-evs-electric-vehicles-20000
A6: 2023 | B6: Tesla cuts new-car prices repeatedly; by 2023-04-06 Reuters counts a fifth cut of the year. Cox says used EV prices follow the market leader's new prices down. | C6: The upstream event that made residual-value constants stale. | D6: Reuters via FXEmpire: https://fxempire.com/news/article/used-u-s-electric-vehicle-sales-jump-as-prices-fall-group-1332056
A7: 2023-01 to 2023-06 | B7: iSeeCars: used EV price decline vs a year earlier accelerated from 8.8% (Jan) to 16.8% (Mar) to 29.5% (Jun). | C7: Public monthly series Drift could fetch to test a residual-value constant. | D7: Autoblog/Yahoo Finance: https://www.autoblog.com/2023/07/16/used-ev-prices-are-collapsing-and-tesla-is-why/
A8: 2023 | B8: CCC report: collision repair on EVs cost about 56% more than on gas cars (2022 data) with about 25% longer repair waits. | C8: Public source for the EV collision-cost uplift constant. | D8: Axios: https://www.axios.com/2024/01/11/hertz-evs-electric-vehicles-20000
A9: 2024-01-11 | B9: Hertz 8-K: sell about 20,000 EVs (about one third of the global EV fleet); about $245M incremental net depreciation in Q4 2023. | C9: The headline loss. A one-cell residual assumption sits behind it. | D9: SEC 8-K: https://www.sec.gov/Archives/edgar/data/1657853/000165785324000010/htz-20240111.htm
A10: 2024-02-06 | B10: Q4 2023: depreciation per unit per month $498 vs $242 a year earlier; fleet interest $91 vs $55 per unit per month; Q4 Adjusted Corporate EBITDA negative $382M including the $245M; full year $561M including the $245M. | C10: Shows TWO more drifted inputs (depreciation and interest cost), not just EVs. | D10: Hertz release: https://www.sec.gov/Archives/edgar/data/1657853/000165785324000019/q42023earningsrelease.htm
A11: 2024-02-06 | B11: Earnings deck: net book value of the 20,000 EVs $787M. | C11: Lets us back out the implied market value per car (see Hertz_Reconciliation). | D11: Q4 2023 deck: https://static.seekingalpha.com/uploads/sa_presentations/924/98924/original.pdf
A12: 2024-Q1 | B12: Hertz raises the 2024 EV disposal plan by 10,000 to 30,000 vehicles; $195M further charge in Q1 2024. | C12: The stale input kept costing money for another quarter. | D12: Q1 2024 release: https://www.sec.gov/Archives/edgar/data/1657853/000165785324000060/q12024earningsrelease.htm
A13: FY2024 10-K | B13: Stated reasons: EV supply exceeded demand, elevated EV damage and collision costs, and declining EV residual values. Carrying value of the first disposal group $542M. | C13: Confirms the three drivers modelled in this workbook. | D13: SEC 10-K / ARS: https://www.sec.gov/Archives/edgar/data/1657853/000110465925033065/tm254478d2_ars.pdf
A14: 2024-06 | B14: Hertz Car Sales lists mostly 2022-23 Teslas at about $21,000 to $36,000. | C14: Retail evidence that the market value was far below the $42,000 cost. | D14: Fortune: https://fortune.com/2024/06/07/buy-used-tesla-hertz-fire-sale

Sheet Inputs
A1: Inputs (as built 2022-12-15)
A2: Blue = hardcoded. Yellow = drifting external assumptions. Mock company; values calibrated to public Hertz figures where noted.
A4: Assumption | B4: Value | C4: Unit | D4: Note
A5: EV average fleet | B5: 60000 | C5: vehicles | D5: Internal plan. About one third of Hertz's disclosed EV fleet implies roughly 60,000.
A6: ICE average fleet | B6: 490000 | C6: vehicles | D6: Internal plan. Total fleet 550,000 (derived from Hertz Q4'23 figures, see Hertz_Reconciliation).
A7: Utilization (days rented / days available) | B7: 0.78 | C7: % | D7: Internal. Hertz Q4'23 revenue per unit per month $1,381 / RPD $58.09 is about 24 days of 30, i.e. about 78%.
A8: Revenue per day (RPD) | B8: 61 | C8: $ / day | D8: Management pricing lever. Hertz reported $58.09 in Q4 2023.
A9: EV acquisition cost | B9: 42000 | C9: $ / car | D9: Historical fact: $4.2B / 100,000 Teslas.
A10: ICE acquisition cost | B10: 33000 | C10: $ / car | D10: Historical fact (mock).
A11: EV residual value at disposal | B11: 0.72 | C11: % of cost | D11: KEY ASSUMPTION. Set when Model 3s were reported to hold about 90% of value at three years (Electrek).
A12: ICE residual value at disposal | B12: 0.82 | C12: % of cost | D12: KEY ASSUMPTION. Gives about $248/unit/month, near Hertz's Q4'22 $242.
A13: EV holding period | B13: 36 | C13: months | D13: Policy.
A14: ICE holding period | B14: 24 | C14: months | D14: Policy.
A15: Average vehicle debt per car | B15: 19400 | C15: $ / car | D15: Internal. Roughly $55/unit/month of interest at 3.4%.
A16: Blended fleet debt cost | B16: 0.034 | C16: % p.a. | D16: KEY ASSUMPTION. Partly hedged ABS debt. Hertz reported $55/unit/month in Q4'22.
... A19: SG&A | B19: 1600 | C19: $M p.a. | D19: Internal (mock).

Sheet Fleet_Model
A1: Fleet economics, FY2024E (rolled forward from FY2023 budget)
A2: Three constants are buried in formulas on purpose: B11 (x1.2), B13 and C13 (x0.015), plus unit constants 365, 12, 1,000,000.
A4: Line item | B4: EV | C4: ICE | D4: Total
A5: Average fleet (vehicles) | B5: =Inputs!B5 -> 60000 | C5: =Inputs!B6 -> 490000 | D5: =B5+C5 -> 550000
A6: Rental days | B6: =B5*365*Inputs!$B$7 -> 17082000 | C6: =C5*365*Inputs!$B$7 -> 139503000 | D6: =B6+C6 -> 156585000
A7: Revenue ($M) | B7: =B6*Inputs!$B$8/1000000 -> 1042.002 | C7: =C6*Inputs!$B$8/1000000 -> 8509.683 | D7: =B7+C7 -> 9551.685
A8: Depreciation per unit per month ($) | B8: =Inputs!B9*(1-Inputs!B11)/Inputs!B13 -> 326.66667 | C8: =Inputs!B10*(1-Inputs!B12)/Inputs!B14 -> 247.5 | D8: =IF(D5=0,0,(B8*B5+C8*C5)/D5) -> 256.13636
A9: Vehicle depreciation ($M) | B9: =B8*B5*12/1000000 -> 235.2 | C9: =C8*C5*12/1000000 -> 1455.3 | D9: =B9+C9 -> 1690.5
A10: Fleet interest ($M) | B10: =B5*Inputs!$B$15*Inputs!$B$16/1000000 -> 39.576 | C10: =C5*Inputs!$B$15*Inputs!$B$16/1000000 -> 323.204 | D10: =B10+C10 -> 362.78
A11: Collision and damage ($M) | B11: =B6*Inputs!$B$17*1.2/1000000 -> 69.69456 | C11: =C6*Inputs!$B$17/1000000 -> 474.3102 | D11: =B11+C11 -> 544.00476
A12: Other direct operating expense ($M) | B12: =B6*Inputs!$B$18/1000000 -> 461.214 | C12: =C6*Inputs!$B$18/1000000 -> 3766.581 | D12: =B12+C12 -> 4227.795
A13: Remarketing and disposal cost ($M) | B13: =B5*12/Inputs!B13*Inputs!B9*Inputs!B11*0.015/1000000 -> 9.072 | C13: =C5*12/Inputs!B14*Inputs!B10*Inputs!B12*0.015/1000000 -> 99.4455 | D13: =B13+C13 -> 108.5175
A14: Segment contribution ($M) | B14: =B7-B9-B10-B11-B12-B13 -> 227.24544 | C14: =C7-C9-C10-C11-C12-C13 -> 2390.8423 | D14: =B14+C14 -> 2618.0877
A15: SG&A ($M) | D15: =Inputs!B19 -> 1600
A16: Adjusted Corporate EBITDA ($M) | D16: =D14-D15 -> 1018.0877
A17: EBITDA margin | D17: =IF(D7=0,0,D16/D7) -> 0.10658724

Sheet Market_Data
A1: Market data (what Drift would fetch)
A2: Monthly series below are SYNTHETIC illustrative paths (direction and end-point calibrated to public reports). Anchors table is sourced; see Status column.
A5: Month-end | B5: Used EV value index (Dec 2022 = 100) | C5: Used ICE value index (Dec 2022 = 100) | D5: 1M Term SOFR (%) approx
A6: 2022-12 | B6: 100 | C6: 100 | D6: 4.3
A7: 2023-01 | B7: 97.5 | C7: 99.7 | D7: 4.31
A8: 2023-02 | B8: 94 | C8: 99.4 | D8: 4.55
A9: 2023-03 | B9: 90 | C9: 99.1 | D9: 4.65
A10: 2023-04 | B10: 86.5 | C10: 98.9 | D10: 4.81
A11: 2023-05 | B11: 83 | C11: 98.8 | D11: 5.05
A12: 2023-06 | B12: 80 | C12: 98.6 | D12: 5.08
A13: 2023-07 | B13: 77.5 | C13: 98.4 | D13: 5.12
A14: 2023-08 | B14: 75.5 | C14: 98.2 | D14: 5.3
A15: 2023-09 | B15: 73.5 | C15: 98 | D15: 5.31
A16: 2023-10 | B16: 72 | C16: 97.9 | D16: 5.31
A17: 2023-11 | B17: 70.5 | C17: 97.7 | D17: 5.32
A18: 2023-12 | B18: 69.4 | C18: 97.6 | D18: 5.31
A21: Anchors (public figures used to calibrate the mock)
A22: Metric | B22: Value | C22: Unit | D22: Period | E22: Source | F22: Status
A23: Fleet interest per unit per month, Q4 2022 | B23: 55 | C23: $ | D23: Q4 2022 | E23: Hertz Q4 2023 release (sec.gov 000165785324000019) | F23: Verified in source
A24: Fleet interest per unit per month, Q4 2023 | B24: 91 | C24: $ | D24: Q4 2023 | E24: Hertz Q4 2023 release (sec.gov 000165785324000019) | F24: Verified in source
A25: Depreciation per unit per month, Q4 2022 | B25: 242 | C25: $ | D25: Q4 2022 | E25: Hertz Q4 2023 release | F25: Verified in source
A26: Depreciation per unit per month, Q4 2023 | B26: 498 | C26: $ | D26: Q4 2023 | E26: Hertz Q4 2023 release | F26: Verified in source
A27: Depreciation per unit per month, Q4 2023, excl. EV sale charge | B27: 350 | C27: $ | D27: Q4 2023 | E27: Hertz Q4 2023 earnings deck (label read from extract; confirm) | F27: Verify label
A28: Revenue per day, Q4 2023 | B28: 58.09 | C28: $ | D28: Q4 2023 | E28: Hertz Q4 2023 release | F28: Verified in source
A29: EV vs gas collision repair cost ratio | B29: 1.56 | C29: x | D29: 2022 data | E29: CCC report, cited by Axios 2024-01-11 | F29: Verified (secondary)
A30: Remarketing fee, % of proceeds | B30: 0.015 | C30: % | D30: 2023 | E30: Mock assumption, held unchanged as a freshness control | F30: Mock
A31: Used EV price change vs prior year, June 2023 | B31: -0.295 | C31: % | D31: 2023-06 | E31: iSeeCars via Autoblog | F31: Verified (secondary)
A32: Average used EV retail listing price, Q1 2023 | B32: 43400 | C32: $ | D32: Q1 2023 | E32: Cox Automotive via Reuters | F32: Verified (secondary)
A33: Hertz Tesla order, vehicles | B33: 100000 | C33: cars | D33: 2021-10 | E33: Fortune / Electrek | F33: Verified (secondary)
A34: Hertz Tesla order, value ($M) | B34: 4200 | C34: $M | D34: 2021-10 | E34: Fortune / Electrek | F34: Verified (secondary)

Sheet Driver_Map
A1: Driver map: GROUND TRUTH answer key for Drift
A2: Col B = the label Drift should propose. Col I = the value it should fetch. Col M = expected verdict. Col N = expected EBITDA impact ($M, one driver at a time).
A4: ID | B4: Real-world driver (semantic label) | C4: Where it lives | D4: As-built value | E4: Unit | F4: Drift-eligible? | G4: Why | H4: Public source to fetch from | I4: Current value | J4: Current as of | K4: % change | L4: Stale threshold | M4: Verdict | N4: EBITDA impact ($M)
A5: D1 | B5: Residual value of a 2-3 year old EV at disposal (as % of cost) | C5: Inputs!B11 | D5: =Inputs!B11 -> 0.72 | E5: % of cost | F5: Y | G5: External market price; moved with Tesla price cuts. | H5: Manheim / Cox Automotive used EV values; iSeeCars used EV price studies | I5: =Inputs!B11*Market_Data!B18/Market_Data!B6 -> 0.49968 | J5: 2023-12 | K5: =IF(D5=0,0,I5/D5-1) -> -0.306 | L5: 0.05 | M5: =IF(OR(ABS(K5)>L5,ABS(N5)>$D$33),"STALE","Fresh") -> STALE | N5: =Impact_Engine!D35 -> -182.29277
A6: D2 | B6: Residual value of a 2 year old gas car at disposal (as % of cost) | C6: Inputs!B12 | D6: =Inputs!B12 -> 0.82 | E6: % of cost | F6: Y | G6: External market price. | H6: Manheim Used Vehicle Value Index | I6: =Inputs!B12*Market_Data!C18/Market_Data!C6 -> 0.80032 | J6: 2023-12 | K6: =IF(D6=0,0,I6/D6-1) -> -0.024 | L6: 0.05 | M6: =IF(OR(ABS(K6)>L6,ABS(N6)>$D$33),"STALE","Fresh") -> STALE | N6: =Impact_Engine!E35 -> -156.72611
A7: D3 | B7: Blended cost of fleet debt (floating-rate ABS, partly hedged) | C7: Inputs!B16 | D7: =Inputs!B16 -> 0.034 | E7: % p.a. | F7: Y | G7: Tracks benchmark rates and ABS spreads. | H7: 1M Term SOFR (FRED) plus peer-reported fleet interest per unit | I7: =Inputs!B16*Market_Data!B24/Market_Data!B23 -> 0.056254545 | J7: 2023-Q4 | K7: =IF(D7=0,0,I7/D7-1) -> 0.65454545 | L7: 0.1 | M7: =IF(OR(ABS(K7)>L7,ABS(N7)>$D$33),"STALE","Fresh") -> STALE | N7: =Impact_Engine!F35 -> -237.456
A8: D4 | B8: EV collision repair cost relative to a gas car | C8: Fleet_Model!B11 (buried constant 1.2) | D8: 1.2 | E8: x | F8: Y | G8: Buried number inside a formula. Drifts with repair-cost data. | H8: CCC Intelligent Solutions crash-course / repair cost reports | I8: =Market_Data!B29 -> 1.56 | J8: 2022 data | K8: =IF(D8=0,0,I8/D8-1) -> 0.3 | L8: 0.1 | M8: =IF(OR(ABS(K8)>L8,ABS(N8)>$D$33),"STALE","Fresh") -> STALE | N8: =Impact_Engine!G35 -> -20.908368
A9: D5 | B9: Remarketing / auction fee as % of sale proceeds | C9: Fleet_Model!B13, C13 (buried constant 0.015) | D9: 0.015 | E9: % | F9: Y | G9: FRESH CONTROL: eligible, but has not moved. Drift should say 'fresh'. | H9: Auction house fee schedules (Manheim, ADESA) | I9: =Market_Data!B30 -> 0.015 | J9: 2023 | K9: =IF(D9=0,0,I9/D9-1) -> 0 | L9: 0.1 | M9: =IF(OR(ABS(K9)>L9,ABS(N9)>$D$33),"STALE","Fresh") -> Fresh | N9: =Impact_Engine!H35 -> 0
A10: D6 | B10: Rental revenue per day | C10: Inputs!B8 | D10: =Inputs!B8 -> 61 | E10: $ / day | F10: N | G10: Management pricing lever. Label it, show the reference value, do not auto-update. | H10: Reference only: peer-reported RPD | I10: =Market_Data!B28 -> 58.09 | J10: 2023-Q4 | K10: =IF(D10=0,0,I10/D10-1) -> -0.047704918 | M10: Label only | N10: =Impact_Engine!J35 -> -455.66235
A11: D7 | B11: EV acquisition cost per car | C11: Inputs!B9 | D11: =Inputs!B9 -> 42000 | E11: $ / car | F11: N | G11: Historical fact. Updating it would be an error. | H11: n/a | M11: Not a market driver
A12: D8 | B12: ICE acquisition cost per car | C12: Inputs!B10 | D12: =Inputs!B10 -> 33000 | E12: $ / car | F12: N | G12: Historical fact. | H12: n/a | M12: Not a market driver
A13: D9 | B13: EV holding period | C13: Inputs!B13 | D13: =Inputs!B13 -> 36 | E13: months | F13: N | G13: Company policy. | H13: n/a | M13: Not a market driver
A14: D10 | B14: ICE holding period | C14: Inputs!B14 | D14: =Inputs!B14 -> 24 | E14: months | F14: N | G14: Company policy. | H14: n/a | M14: Not a market driver
A15: D11 | B15: Fleet utilization | C15: Inputs!B7 | D15: =Inputs!B7 -> 0.78 | E15: % | F15: N | G15: Internal operating metric. | H15: n/a | M15: Not a market driver
A16: D12 | B16: EV fleet size | C16: Inputs!B5 | D16: =Inputs!B5 -> 60000 | E16: vehicles | F16: N | G16: Internal plan. | H16: n/a | M16: Not a market driver
A17: D13 | B17: ICE fleet size | C17: Inputs!B6 | D17: =Inputs!B6 -> 490000 | E17: vehicles | F17: N | G17: Internal plan. | H17: n/a | M17: Not a market driver
A18: D14 | B18: Average debt per car | C18: Inputs!B15 | D18: =Inputs!B15 -> 19400 | E18: $ / car | F18: N | G18: Internal balance-sheet figure. | H18: n/a | M18: Not a market driver
A19: D15 | B19: ICE collision cost per day | C19: Inputs!B17 | D19: =Inputs!B17 -> 3.4 | E19: $ / day | F19: N | G19: Internal cost. | H19: n/a | M19: Not a market driver
A20: D16 | B20: Other direct operating cost per day | C20: Inputs!B18 | D20: =Inputs!B18 -> 27 | E20: $ / day | F20: N | G20: Internal cost. | H20: n/a | M20: Not a market driver
A21: D17 | B21: SG&A | C21: Inputs!B19 | D21: =Inputs!B19 -> 1600 | E21: $M | F21: N | G21: Internal budget. | H21: n/a | M21: Not a market driver
A22: D18 | B22: Days per year (365) | C22: Fleet_Model!B6, C6 (buried) | D22: 365 | E22: days | F22: N | G22: Unit constant, not an assumption. | H22: n/a | M22: Not a market driver
A23: D19 | B23: Months per year (12) | C23: Fleet_Model rows 9, 13 (buried) | D23: 12 | E23: months | F23: N | G23: Unit constant. | H23: n/a | M23: Not a market driver
A24: D20 | B24: Dollars to $M scaling (1,000,000) | C24: Fleet_Model rows 7-13 (buried) | D24: 1000000 | E24: scalar | F24: N | G24: Unit constant. | H24: n/a | M24: Not a market driver
A27: Summary
B28: EBITDA as built ($M) | D28: =Impact_Engine!C34 -> 1018.0877
B29: EBITDA with all stale external drivers refreshed ($M) | D29: =Impact_Engine!I34 -> 420.7045
B30: Total change ($M) | D30: =D29-D28 -> -597.38324
B31: Change as % of as-built EBITDA | D31: =IF(D28=0,0,D30/D28) -> -0.5867699
B32: Materiality: % of as-built EBITDA | D32: 0.05
B33: Materiality threshold ($M) | D33: =D32*D28 -> 50.904387
B34: Verdict rule: STALE if the input moved more than its threshold (col L) OR moving it changes EBITDA by more than the materiality threshold. D2 shows why: only 2.4% drift, but about $157M of EBITDA.

Sheet Impact_Engine
A1: Impact engine: re-runs the model with one driver refreshed at a time
A2: Same logic as Fleet_Model. Column C must equal Fleet_Model EBITDA (check in C37).
A4: Line | B4: Unit | C4: As built | D4: EV residual | E4: ICE residual | F4: Fleet debt cost | G4: EV collision uplift | H4: Remarketing fee (control) | I4: ALL external refreshed | J4: RPD (mgmt lever, ref only)
A5: Inputs by scenario
A6: EV fleet | B6: vehicles | C6: =Inputs!$B$5 -> 60000 | D6: =Inputs!$B$5 -> 60000 | E6: =Inputs!$B$5 -> 60000 | F6: =Inputs!$B$5 -> 60000 | G6: =Inputs!$B$5 -> 60000 | H6: =Inputs!$B$5 -> 60000 | I6: =Inputs!$B$5 -> 60000 | J6: =Inputs!$B$5 -> 60000
A7: ICE fleet | B7: vehicles | C7: =Inputs!$B$6 -> 490000 | D7: =Inputs!$B$6 -> 490000 | E7: =Inputs!$B$6 -> 490000 | F7: =Inputs!$B$6 -> 490000 | G7: =Inputs!$B$6 -> 490000 | H7: =Inputs!$B$6 -> 490000 | I7: =Inputs!$B$6 -> 490000 | J7: =Inputs!$B$6 -> 490000
A8: Utilization | B8: % | C8: =Inputs!$B$7 -> 0.78 | D8: =Inputs!$B$7 -> 0.78 | E8: =Inputs!$B$7 -> 0.78 | F8: =Inputs!$B$7 -> 0.78 | G8: =Inputs!$B$7 -> 0.78 | H8: =Inputs!$B$7 -> 0.78 | I8: =Inputs!$B$7 -> 0.78 | J8: =Inputs!$B$7 -> 0.78
A9: Revenue per day | B9: $ | C9: =Inputs!$B$8 -> 61 | D9: =Inputs!$B$8 -> 61 | E9: =Inputs!$B$8 -> 61 | F9: =Inputs!$B$8 -> 61 | G9: =Inputs!$B$8 -> 61 | H9: =Inputs!$B$8 -> 61 | I9: =Inputs!$B$8 -> 61 | J9: =Driver_Map!$I$10 -> 58.09
A10: EV acquisition cost | B10: $ | C10: =Inputs!$B$9 -> 42000 | D10: =Inputs!$B$9 -> 42000 | E10: =Inputs!$B$9 -> 42000 | F10: =Inputs!$B$9 -> 42000 | G10: =Inputs!$B$9 -> 42000 | H10: =Inputs!$B$9 -> 42000 | I10: =Inputs!$B$9 -> 42000 | J10: =Inputs!$B$9 -> 42000
A11: ICE acquisition cost | B11: $ | C11: =Inputs!$B$10 -> 33000 | D11: =Inputs!$B$10 -> 33000 | E11: =Inputs!$B$10 -> 33000 | F11: =Inputs!$B$10 -> 33000 | G11: =Inputs!$B$10 -> 33000 | H11: =Inputs!$B$10 -> 33000 | I11: =Inputs!$B$10 -> 33000 | J11: =Inputs!$B$10 -> 33000
A12: EV residual | B12: % | C12: =Inputs!$B$11 -> 0.72 | D12: =Driver_Map!$I$5 -> 0.49968 | E12: =Inputs!$B$11 -> 0.72 | F12: =Inputs!$B$11 -> 0.72 | G12: =Inputs!$B$11 -> 0.72 | H12: =Inputs!$B$11 -> 0.72 | I12: =Driver_Map!$I$5 -> 0.49968 | J12: =Inputs!$B$11 -> 0.72
A13: ICE residual | B13: % | C13: =Inputs!$B$12 -> 0.82 | D13: =Inputs!$B$12 -> 0.82 | E13: =Driver_Map!$I$6 -> 0.80032 | F13: =Inputs!$B$12 -> 0.82 | G13: =Inputs!$B$12 -> 0.82 | H13: =Inputs!$B$12 -> 0.82 | I13: =Driver_Map!$I$6 -> 0.80032 | J13: =Inputs!$B$12 -> 0.82
A14: EV holding period | B14: months | C14: =Inputs!$B$13 -> 36 | D14: =Inputs!$B$13 -> 36 | E14: =Inputs!$B$13 -> 36 | F14: =Inputs!$B$13 -> 36 | G14: =Inputs!$B$13 -> 36 | H14: =Inputs!$B$13 -> 36 | I14: =Inputs!$B$13 -> 36 | J14: =Inputs!$B$13 -> 36
A15: ICE holding period | B15: months | C15: =Inputs!$B$14 -> 24 | D15: =Inputs!$B$14 -> 24 | E15: =Inputs!$B$14 -> 24 | F15: =Inputs!$B$14 -> 24 | G15: =Inputs!$B$14 -> 24 | H15: =Inputs!$B$14 -> 24 | I15: =Inputs!$B$14 -> 24 | J15: =Inputs!$B$14 -> 24
A16: Debt per car | B16: $ | C16: =Inputs!$B$15 -> 19400 | D16: =Inputs!$B$15 -> 19400 | E16: =Inputs!$B$15 -> 19400 | F16: =Inputs!$B$15 -> 19400 | G16: =Inputs!$B$15 -> 19400 | H16: =Inputs!$B$15 -> 19400 | I16: =Inputs!$B$15 -> 19400 | J16: =Inputs!$B$15 -> 19400
A17: Fleet debt cost | B17: % | C17: =Inputs!$B$16 -> 0.034 | D17: =Inputs!$B$16 -> 0.034 | E17: =Inputs!$B$16 -> 0.034 | F17: =Driver_Map!$I$7 -> 0.056254545 | G17: =Inputs!$B$16 -> 0.034 | H17: =Inputs!$B$16 -> 0.034 | I17: =Driver_Map!$I$7 -> 0.056254545 | J17: =Inputs!$B$16 -> 0.034
A18: ICE collision cost per day | B18: $ | C18: =Inputs!$B$17 -> 3.4 | D18: =Inputs!$B$17 -> 3.4 | E18: =Inputs!$B$17 -> 3.4 | F18: =Inputs!$B$17 -> 3.4 | G18: =Inputs!$B$17 -> 3.4 | H18: =Inputs!$B$17 -> 3.4 | I18: =Inputs!$B$17 -> 3.4 | J18: =Inputs!$B$17 -> 3.4
A19: Other DOE per day | B19: $ | C19: =Inputs!$B$18 -> 27 | D19: =Inputs!$B$18 -> 27 | E19: =Inputs!$B$18 -> 27 | F19: =Inputs!$B$18 -> 27 | G19: =Inputs!$B$18 -> 27 | H19: =Inputs!$B$18 -> 27 | I19: =Inputs!$B$18 -> 27 | J19: =Inputs!$B$18 -> 27
A20: SG&A | B20: $M | C20: =Inputs!$B$19 -> 1600 | D20: =Inputs!$B$19 -> 1600 | E20: =Inputs!$B$19 -> 1600 | F20: =Inputs!$B$19 -> 1600 | G20: =Inputs!$B$19 -> 1600 | H20: =Inputs!$B$19 -> 1600 | I20: =Inputs!$B$19 -> 1600 | J20: =Inputs!$B$19 -> 1600
A21: EV collision uplift | B21: x | C21: =Driver_Map!$D$8 -> 1.2 | D21: =Driver_Map!$D$8 -> 1.2 | E21: =Driver_Map!$D$8 -> 1.2 | F21: =Driver_Map!$D$8 -> 1.2 | G21: =Driver_Map!$I$8 -> 1.56 | H21: =Driver_Map!$D$8 -> 1.2 | I21: =Driver_Map!$I$8 -> 1.56 | J21: =Driver_Map!$D$8 -> 1.2
A22: Remarketing fee | B22: % | C22: =Driver_Map!$D$9 -> 0.015 | D22: =Driver_Map!$D$9 -> 0.015 | E22: =Driver_Map!$D$9 -> 0.015 | F22: =Driver_Map!$D$9 -> 0.015 | G22: =Driver_Map!$D$9 -> 0.015 | H22: =Driver_Map!$I$9 -> 0.015 | I22: =Driver_Map!$I$9 -> 0.015 | J22: =Driver_Map!$D$9 -> 0.015
A23: Calculation
A24: EV rental days | B24: days | C24: =C6*365*C8 -> 17082000 | D24: =D6*365*D8 -> 17082000 | E24: =E6*365*E8 -> 17082000 | F24: =F6*365*F8 -> 17082000 | G24: =G6*365*G8 -> 17082000 | H24: =H6*365*H8 -> 17082000 | I24: =I6*365*I8 -> 17082000 | J24: =J6*365*J8 -> 17082000
A25: ICE rental days | B25: days | C25: =C7*365*C8 -> 139503000 | D25: =D7*365*D8 -> 139503000 | E25: =E7*365*E8 -> 139503000 | F25: =F7*365*F8 -> 139503000 | G25: =G7*365*G8 -> 139503000 | H25: =H7*365*H8 -> 139503000 | I25: =I7*365*I8 -> 139503000 | J25: =J7*365*J8 -> 139503000
A26: Revenue | B26: $M | C26: =(C24+C25)*C9/1000000 -> 9551.685 | D26: =(D24+D25)*D9/1000000 -> 9551.685 | E26: =(E24+E25)*E9/1000000 -> 9551.685 | F26: =(F24+F25)*F9/1000000 -> 9551.685 | G26: =(G24+G25)*G9/1000000 -> 9551.685 | H26: =(H24+H25)*H9/1000000 -> 9551.685 | I26: =(I24+I25)*I9/1000000 -> 9551.685 | J26: =(J24+J25)*J9/1000000 -> 9096.0227
A27: EV depreciation | B27: $M | C27: =C10*(1-C12)/C14*C6*12/1000000 -> 235.2 | D27: =D10*(1-D12)/D14*D6*12/1000000 -> 420.2688 | E27: =E10*(1-E12)/E14*E6*12/1000000 -> 235.2 | F27: =F10*(1-F12)/F14*F6*12/1000000 -> 235.2 | G27: =G10*(1-G12)/G14*G6*12/1000000 -> 235.2 | H27: =H10*(1-H12)/H14*H6*12/1000000 -> 235.2 | I27: =I10*(1-I12)/I14*I6*12/1000000 -> 420.2688 | J27: =J10*(1-J12)/J14*J6*12/1000000 -> 235.2
A28: ICE depreciation | B28: $M | C28: =C11*(1-C13)/C15*C7*12/1000000 -> 1455.3 | D28: =D11*(1-D13)/D15*D7*12/1000000 -> 1455.3 | E28: =E11*(1-E13)/E15*E7*12/1000000 -> 1614.4128 | F28: =F11*(1-F13)/F15*F7*12/1000000 -> 1455.3 | G28: =G11*(1-G13)/G15*G7*12/1000000 -> 1455.3 | H28: =H11*(1-H13)/H15*H7*12/1000000 -> 1455.3 | I28: =I11*(1-I13)/I15*I7*12/1000000 -> 1614.4128 | J28: =J11*(1-J13)/J15*J7*12/1000000 -> 1455.3
A29: Fleet interest | B29: $M | C29: =(C6+C7)*C16*C17/1000000 -> 362.78 | D29: =(D6+D7)*D16*D17/1000000 -> 362.78 | E29: =(E6+E7)*E16*E17/1000000 -> 362.78 | F29: =(F6+F7)*F16*F17/1000000 -> 600.236 | G29: =(G6+G7)*G16*G17/1000000 -> 362.78 | H29: =(H6+H7)*H16*H17/1000000 -> 362.78 | I29: =(I6+I7)*I16*I17/1000000 -> 600.236 | J29: =(J6+J7)*J16*J17/1000000 -> 362.78
A30: Collision and damage | B30: $M | C30: =(C24*C21+C25)*C18/1000000 -> 544.00476 | D30: =(D24*D21+D25)*D18/1000000 -> 544.00476 | E30: =(E24*E21+E25)*E18/1000000 -> 544.00476 | F30: =(F24*F21+F25)*F18/1000000 -> 544.00476 | G30: =(G24*G21+G25)*G18/1000000 -> 564.91313 | H30: =(H24*H21+H25)*H18/1000000 -> 544.00476 | I30: =(I24*I21+I25)*I18/1000000 -> 564.91313 | J30: =(J24*J21+J25)*J18/1000000 -> 544.00476
A31: Other DOE | B31: $M | C31: =(C24+C25)*C19/1000000 -> 4227.795 | D31: =(D24+D25)*D19/1000000 -> 4227.795 | E31: =(E24+E25)*E19/1000000 -> 4227.795 | F31: =(F24+F25)*F19/1000000 -> 4227.795 | G31: =(G24+G25)*G19/1000000 -> 4227.795 | H31: =(H24+H25)*H19/1000000 -> 4227.795 | I31: =(I24+I25)*I19/1000000 -> 4227.795 | J31: =(J24+J25)*J19/1000000 -> 4227.795
A32: Remarketing and disposal | B32: $M | C32: =(C6*12/C14*C10*C12+C7*12/C15*C11*C13)*C22/1000000 -> 108.5175 | D32: =(D6*12/D14*D10*D12+D7*12/D15*D11*D13)*D22/1000000 -> 105.74147 | E32: =(E6*12/E14*E10*E12+E7*12/E15*E11*E13)*E22/1000000 -> 106.13081 | F32: =(F6*12/F14*F10*F12+F7*12/F15*F11*F13)*F22/1000000 -> 108.5175 | G32: =(G6*12/G14*G10*G12+G7*12/G15*G11*G13)*G22/1000000 -> 108.5175 | H32: =(H6*12/H14*H10*H12+H7*12/H15*H11*H13)*H22/1000000 -> 108.5175 | I32: =(I6*12/I14*I10*I12+I7*12/I15*I11*I13)*I22/1000000 -> 103.35478 | J32: =(J6*12/J14*J10*J12+J7*12/J15*J11*J13)*J22/1000000 -> 108.5175
A33: SG&A | B33: $M | C33: =C20 -> 1600 | D33: =D20 -> 1600 | E33: =E20 -> 1600 | F33: =F20 -> 1600 | G33: =G20 -> 1600 | H33: =H20 -> 1600 | I33: =I20 -> 1600 | J33: =J20 -> 1600
A34: Adjusted Corporate EBITDA | B34: $M | C34: =C26-C27-C28-C29-C30-C31-C32-C33 -> 1018.0877 | D34: =D26-D27-D28-D29-D30-D31-D32-D33 -> 835.79497 | E34: =E26-E27-E28-E29-E30-E31-E32-E33 -> 861.36163 | F34: =F26-F27-F28-F29-F30-F31-F32-F33 -> 780.63174 | G34: =G26-G27-G28-G29-G30-G31-G32-G33 -> 997.17937 | H34: =H26-H27-H28-H29-H30-H31-H32-H33 -> 1018.0877 | I34: =I26-I27-I28-I29-I30-I31-I32-I33 -> 420.7045 | J34: =J26-J27-J28-J29-J30-J31-J32-J33 -> 562.42539
A35: Change vs as built | B35: $M | C35: =C34-$C$34 -> 0 | D35: =D34-$C$34 -> -182.29277 | E35: =E34-$C$34 -> -156.72611 | F35: =F34-$C$34 -> -237.456 | G35: =G34-$C$34 -> -20.908368 | H35: =H34-$C$34 -> 0 | I35: =I34-$C$34 -> -597.38324 | J35: =J34-$C$34 -> -455.66235
A37: Check: engine as-built minus Fleet_Model EBITDA (should be 0) | C37: =ROUND(C34-Fleet_Model!D16,6) -> 0
A38: Check: sum of one-at-a-time impacts minus joint impact (should be 0) | C38: =ROUND(D35+E35+F35+G35+H35-I35,6) -> 0

Sheet Hertz_Reconciliation
A1: Reproducing Hertz's $245M from its own disclosures
A2: Demo punchline: public inputs + one market price reproduce the loss. Blue = disclosed figure.
A4: Item | B4: Value | C4: Unit | D4: Note / source
A5: EVs held for sale | B5: 20000 | C5: cars | D5: Hertz 8-K 2024-01-11
A6: Net book value of those EVs | B6: 787 | C6: $M | D6: Q4 2023 earnings deck
A7: Incremental net depreciation recognised Q4 2023 | B7: 245 | C7: $M | D7: Hertz 8-K and Q4 release
A8: Carrying value after write-down (first disposal group) | B8: 542 | C8: $M | D8: FY2024 10-K note
A9: Original cost per EV | B9: =Driver_Map!D11 -> 42000 | C9: $ / car | D9: $4.2B / 100,000
A10: Net book value per EV | B10: =B6*1000000/B5 -> 39350 | C10: $ / car | D10: calc
A11: Implied fair value per EV (carrying value after write-down) | B11: =B8*1000000/B5 -> 27100 | C11: $ / car | D11: calc
A12: Write-down per EV | B12: =B10-B11 -> 12250 | C12: $ / car | D12: calc
A13: Implied fair value as % of original cost | B13: =B11/B9 -> 0.6452381 | C13: % | D13: Compare with the 72% residual assumed at 36 months in the model
A14: Check: NBV less carrying value less reported charge (should be 0) | B14: =ROUND(B6-B8-B7,6) -> 0 | C14: $M | D14: Disclosures reconcile
A16: Q4 2023 depreciation per unit per month | B16: =Market_Data!B26 -> 498 | C16: $ | D16: Hertz Q4 release
A17: Q4 2023 depreciation per unit per month excl. EV sale charge | B17: =Market_Data!B27 -> 350 | C17: $ | D17: Earnings deck (confirm label)
A18: EV sale charge in DPU terms | B18: =B16-B17 -> 148 | C18: $ | D18: calc
A19: Implied average fleet (vehicles) | B19: =B7*1000000/(B18*3) -> 551801.8 | C19: cars | D19: Derived: $245M / ($148 x 3 months). Mock model uses 550,000.
